[
  {
    "id": "e1c6f0bf733d",
    "title": "US-Iran Seeking Changes to Draft Agreement, Oil Climbs, More",
    "summary": "Source: Bloomberg, 5:48",
    "link": "https://www.bloomberg.com/news/audio/2026-06-01/us-iran-seeking-changes-to-draft-agreement-oil-climbs-more",
    "published": "Mon, 01 Jun 2026 03:21:34 GMT",
    "source": "Bloomberg",
    "fetched_at": "2026-06-01T04:49:10.608388"
  },
  {
    "id": "cc8042906345",
    "title": "Hanwha Aerospace Explosion Prompts President Lee to Order Probe",
    "summary": "Hanwha Aerospace Co. confirmed that an explosion occurred at its facility in Daejeon in central South Korea on Monday, as emergency authorities responded to reports of a blast and heavy smoke at the site.",
    "link": "https://www.bloomberg.com/news/articles/2026-06-01/hanwha-aerospace-explosion-prompts-president-lee-to-order-probe",
    "published": "Mon, 01 Jun 2026 03:19:48 GMT",
    "source": "Bloomberg",
    "fetched_at": "2026-06-01T04:49:10.608401"
  },
  {
    "id": "2e4070a7f651",
    "title": "Regulators Didn’t Speak to US Fund at Heart of Segantii Trial",
    "summary": "The insider trading trial of hedge fund Segantii Capital Management enters a critical moment this week, as the prosecution wraps up its side of the case following testimony from an official at Hong Kong’s securities regulator.",
    "link": "https://www.bloomberg.com/news/articles/2026-06-01/regulators-didn-t-speak-to-us-fund-at-heart-of-segantii-trial",
    "published": "Mon, 01 Jun 2026 02:48:35 GMT",
    "source": "Bloomberg",
    "fetched_at": "2026-06-01T04:49:10.608407"
  },
  {
    "id": "f1b902505e3a",
    "title": "US-Iran Trade Messages on Deal, Oil Rises on Uncertainty, More",
    "summary": "Source: Bloomberg, 5:48",
    "link": "https://www.bloomberg.com/news/audio/2026-06-01/us-iran-trade-messages-on-deal-oil-rises-on-uncertainty-more",
    "published": "Mon, 01 Jun 2026 02:44:13 GMT",
    "source": "Bloomberg",
    "fetched_at": "2026-06-01T04:49:10.608413"
  },
  {
    "id": "375211cd2a07",
    "title": "Weak Monsoon Forecast Adds to India’s Inflation, Growth Worries",
    "summary": "The biggest risk is to rural consumption, a key driver of economic growth.",
    "link": "https://www.bloomberg.com/news/newsletters/2026-06-01/weak-monsoon-may-deepen-india-inflation-risk-force-rbi-s-hand-on-interest-rates",
    "published": "Mon, 01 Jun 2026 02:35:48 GMT",
    "source": "Bloomberg",
    "fetched_at": "2026-06-01T04:49:10.608418"
  },
  {
    "id": "44d3230626e4",
    "title": "SoftBank Set to Dethrone Toyota as Japan’s Most Valuable Company",
    "summary": "SoftBank Group Corp. is poised to overtake Toyota Motor Corp. as Japan’s most valuable company, marking a milestone for the global artificial intelligence boom and a dramatic reshuffling of the country’s corporate hierarchy.",
    "link": "https://www.bloomberg.com/news/articles/2026-06-01/softbank-set-to-dethrone-toyota-as-japan-s-most-valuable-company",
    "published": "Mon, 01 Jun 2026 02:33:30 GMT",
    "source": "Bloomberg",
    "fetched_at": "2026-06-01T04:49:10.608424"
  },
  {
    "id": "e554a67c3212",
    "title": "Top Tech Fund Plans to Buy SK Hynix in Bet on Memory Chip Crunch",
    "summary": "A top-performing technology fund plans to own SK Hynix Inc.’s shares, betting that tighter supply will further benefit the South Korean AI memory chipmaker after a 1,000% rally in the past year.",
    "link": "https://www.bloomberg.com/news/articles/2026-06-01/top-tech-fund-plans-to-buy-sk-hynix-in-bet-on-memory-chip-crunch",
    "published": "Mon, 01 Jun 2026 02:28:03 GMT",
    "source": "Bloomberg",
    "fetched_at": "2026-06-01T04:49:10.608429"
  },
  {
    "id": "a00ec8fce96d",
    "title": "Oil Climbs Higher, US-Iran Exchange Messages on Deal, More",
    "summary": "Source: Bloomberg, 5:05",
    "link": "https://www.bloomberg.com/news/audio/2026-06-01/oil-climbs-higher-us-iran-exchange-messages-on-deal-more",
    "published": "Mon, 01 Jun 2026 01:54:52 GMT",
    "source": "Bloomberg",
    "fetched_at": "2026-06-01T04:49:10.608438"
  },
  {
    "id": "56a0f18b3a4a",
    "title": "Bloomberg Daybreak Asia: US-Iran Deal Still Elusive (Podcast)",
    "summary": "Source: Bloomberg, 15:40",
    "link": "https://www.bloomberg.com/news/audio/2026-06-01/bloomberg-daybreak-asia-us-iran-deal-still-elusive-podcast",
    "published": "Mon, 01 Jun 2026 01:11:22 GMT",
    "source": "Bloomberg",
    "fetched_at": "2026-06-01T04:49:10.608444"
  },
  {
    "id": "b240db34e01f",
    "title": "Oil Moves Higher, US-Iran Trade Drafts of Deal, More",
    "summary": "Source: Bloomberg, 5:16",
    "link": "https://www.bloomberg.com/news/audio/2026-06-01/oil-moves-higher-us-iran-trade-drafts-of-deal-more",
    "published": "Mon, 01 Jun 2026 01:00:59 GMT",
    "source": "Bloomberg",
    "fetched_at": "2026-06-01T04:49:10.608449"
  },
  {
    "id": "352db29b61f5",
    "title": "Berkshire Hathaway to Buy Taylor Morrison for $6.8 Billion",
    "summary": "Berkshire Hathaway Inc. will acquire Taylor Morrison Home Corp. in an all-cash deal worth about $6.8 billion, the first major purchase under chief executive Greg Abel and a vote of confidence in the US housing market.",
    "link": "https://www.bloomberg.com/news/articles/2026-05-31/berkshire-hathaway-to-buy-taylor-morrison-for-6-8-billion",
    "published": "Sun, 31 May 2026 20:40:05 GMT",
    "source": "Bloomberg",
    "fetched_at": "2026-06-01T04:49:10.608455"
  },
  {
    "id": "e10a574e09fa",
    "title": "Oil Climbs, US and Iran Trade Messages But No Deal, More",
    "summary": "Source: Bloomberg, 4:58",
    "link": "https://www.bloomberg.com/news/audio/2026-06-01/oil-climbs-us-and-iran-trade-messages-but-no-deal-more",
    "published": "Mon, 01 Jun 2026 00:02:52 GMT",
    "source": "Bloomberg",
    "fetched_at": "2026-06-01T04:49:10.608460"
  },
  {
    "id": "9ddc1372c1db",
    "title": "US-Iran Trade Drafts of Deal, Israel's Lebanon Offensive, More",
    "summary": "Source: Bloomberg, 5:11",
    "link": "https://www.bloomberg.com/news/audio/2026-05-31/us-iran-trade-drafts-of-deal-israel-s-lebanon-offensive-more",
    "published": "Sun, 31 May 2026 23:03:15 GMT",
    "source": "Bloomberg",
    "fetched_at": "2026-06-01T04:49:10.608465"
  },
  {
    "id": "1784a600f0fe",
    "title": "Sydney, Melbourne House Prices Keep Sliding as Borrowing Costs, Tax Changes Weigh on Demand",
    "summary": "Get caught up.",
    "link": "https://www.bloomberg.com/news/newsletters/2026-05-31/australia-house-prices-superannuation-fears-underwater-drone-investment",
    "published": "Sun, 31 May 2026 22:47:30 GMT",
    "source": "Bloomberg",
    "fetched_at": "2026-06-01T04:49:10.608470"
  },
  {
    "id": "e471204d132b",
    "title": "US-Iran Trade Drafts, Israel Expands Lebanon Offensive, More",
    "summary": "Source: Bloomberg, 5:17",
    "link": "https://www.bloomberg.com/news/audio/2026-05-31/us-iran-trade-drafts-israel-expands-lebanon-offensive-more",
    "published": "Sun, 31 May 2026 22:09:45 GMT",
    "source": "Bloomberg",
    "fetched_at": "2026-06-01T04:49:10.608475"
  },
  {
    "id": "442f64bc989a",
    "title": "Petrobras Cuts Diesel Prices Amid Federal Subsidy Plan",
    "summary": "Brazil’s state-controlled oil giant Petroleo Brasileiro SA is reducing domestic diesel prices starting Monday as part of a government subsidy program to shield consumers from the war in the Middle East.",
    "link": "https://www.bloomberg.com/news/articles/2026-05-31/petrobras-cuts-diesel-prices-amid-federal-subsidy-plan",
    "published": "Sun, 31 May 2026 21:35:03 GMT",
    "source": "Bloomberg",
    "fetched_at": "2026-06-01T04:49:10.608480"
  },
  {
    "id": "d67c77e85a9e",
    "title": "China’s Factory Activity Slows as Mideast War Costs Spread",
    "summary": "Get caught up.",
    "link": "https://www.bloomberg.com/news/newsletters/2026-05-31/eco-data-china-s-factory-activity-slows-as-mideast-war-costs-spread",
    "published": "Sun, 31 May 2026 21:30:48 GMT",
    "source": "Bloomberg",
    "fetched_at": "2026-06-01T04:49:10.608485"
  },
  {
    "id": "94308b1701cc",
    "title": "Israel Expands Lebanon Strikes, Trump Wants Iran Deal Edits",
    "summary": "Source: Bloomberg, 4:57",
    "link": "https://www.bloomberg.com/news/audio/2026-05-31/israel-expands-lebanon-strikes-trump-wants-iran-deal-edits",
    "published": "Sun, 31 May 2026 21:03:03 GMT",
    "source": "Bloomberg",
    "fetched_at": "2026-06-01T04:49:10.608490"
  },
  {
    "id": "16704ca8f19b",
    "title": "Mexico’s Fibra MTY to Buy Fibra Macquarie in $1.7 Billion Deal",
    "summary": "Mexican real estate investment trust Fibra MTY said it’s acquiring peer Fibra Macquarie after the latter’s shareholders backed the transaction.",
    "link": "https://www.bloomberg.com/news/articles/2026-05-31/mexico-s-fibra-mty-to-buy-fibra-macquarie-in-1-7-billion-deal",
    "published": "Sun, 31 May 2026 20:11:48 GMT",
    "source": "Bloomberg",
    "fetched_at": "2026-06-01T04:49:10.608495"
  },
  {
    "id": "4b783599e9c2",
    "title": "A Tight CFO Market Is Driving More Companies to Interim Finance Chiefs",
    "summary": "Interim CFOs accounted for 12% of new finance chief appointments in the first quarter, double the level from a year earlier.",
    "link": "https://www.bloomberg.com/news/newsletters/2026-05-31/interim-cfo-appointments-double-as-executive-searches-drag-on",
    "published": "Sun, 31 May 2026 20:00:02 GMT",
    "source": "Bloomberg",
    "fetched_at": "2026-06-01T04:49:10.608500"
  },
  {
    "id": "112eaa4efa31",
    "title": "Israel Expands Lebanon Assault, Trump Requests Iran Deal Edits",
    "summary": "Source: Bloomberg, 0:00",
    "link": "https://www.bloomberg.com/news/audio/2026-05-31/israel-expands-lebanon-assault-trump-requests-iran-deal-edits",
    "published": "Sun, 31 May 2026 19:47:58 GMT",
    "source": "Bloomberg",
    "fetched_at": "2026-06-01T04:49:10.608505"
  },
  {
    "id": "75b6e566266a",
    "title": "NJ Transit Resumes Service With Delays After Another Fire",
    "summary": "New Jersey Transit trains have resumed system-wide service on Sunday after a fire caused disruptions to the public transit system just days after a separate incident snarled service.",
    "link": "https://www.bloomberg.com/news/articles/2026-05-31/nj-transit-resumes-service-with-delays-after-another-fire",
    "published": "Sun, 31 May 2026 18:15:39 GMT",
    "source": "Bloomberg",
    "fetched_at": "2026-06-01T04:49:10.608510"
  },
  {
    "id": "9b7cf8606f49",
    "title": "Trump Wants Iran Deal Edits, Israel Expands Attacks in Lebanon",
    "summary": "Source: Bloomberg, 0:00",
    "link": "https://www.bloomberg.com/news/audio/2026-05-31/trump-wants-iran-deal-edits-israel-expands-attacks-in-lebanon-mpu14scd",
    "published": "Sun, 31 May 2026 17:04:16 GMT",
    "source": "Bloomberg",
    "fetched_at": "2026-06-01T04:49:10.608519"
  },
  {
    "id": "a4911c1f2a00",
    "title": "Low-Budget Horror Films From YouTubers Conquer the Box Office",
    "summary": "Backrooms, a film based on 20-year-old Kane Parsons’s popular YouTube series of the same name, debuted to $81.4 million at the US and Canada box office this weekend, setting a record for independent distributor A24.",
    "link": "https://www.bloomberg.com/news/articles/2026-05-31/low-budget-horror-films-from-youtubers-conquer-the-box-office",
    "published": "Sun, 31 May 2026 16:27:25 GMT",
    "source": "Bloomberg",
    "fetched_at": "2026-06-01T04:49:10.608523"
  },
  {
    "id": "7b2d6b9626db",
    "title": "Trump Demands Tougher Terms on Iran, Israel Hits Hezbollah, More",
    "summary": "Source: Bloomberg, 0:00",
    "link": "https://www.bloomberg.com/news/audio/2026-05-31/trump-demands-tougher-terms-on-iran-israel-hits-hezbollah-more-mptxsvo5",
    "published": "Sun, 31 May 2026 15:31:01 GMT",
    "source": "Bloomberg",
    "fetched_at": "2026-06-01T04:49:10.608528"
  },
  {
    "id": "6e6fa89e136a",
    "title": "Bloomberg This Weekend: Trump Sends Mixed Signs on War (Podcast)",
    "summary": "Source: Bloomberg, 41:08",
    "link": "https://www.bloomberg.com/news/audio/2026-05-31/bloomberg-this-weekend-trump-sends-mixed-signs-on-war-podcast",
    "published": "Sun, 31 May 2026 14:59:04 GMT",
    "source": "Bloomberg",
    "fetched_at": "2026-06-01T04:49:10.608534"
  },
  {
    "id": "704cc18f13dc",
    "title": "Trump Wants Iran Deal Edits, Israel Expands Attacks in Lebanon",
    "summary": "Source: Bloomberg, 0:00",
    "link": "https://www.bloomberg.com/news/audio/2026-05-31/trump-wants-iran-deal-edits-israel-expands-attacks-in-lebanon-mptvtqtu",
    "published": "Sun, 31 May 2026 14:35:43 GMT",
    "source": "Bloomberg",
    "fetched_at": "2026-06-01T04:49:10.608538"
  },
  {
    "id": "ff17fdddf96f",
    "title": "Trump Demands Tougher Terms on Iran, Israel Hits Hezbollah, More",
    "summary": "Source: Bloomberg, 0:00",
    "link": "https://www.bloomberg.com/news/audio/2026-05-31/trump-demands-tougher-terms-on-iran-israel-hits-hezbollah-more",
    "published": "Sun, 31 May 2026 13:14:36 GMT",
    "source": "Bloomberg",
    "fetched_at": "2026-06-01T04:49:10.608543"
  },
  {
    "id": "db70a096c9f8",
    "title": "Trump Wants Iran Deal Edits, Israel Expands Attacks in Lebanon",
    "summary": "Source: Bloomberg, 0:00",
    "link": "https://www.bloomberg.com/news/audio/2026-05-31/trump-wants-iran-deal-edits-israel-expands-attacks-in-lebanon",
    "published": "Sun, 31 May 2026 11:58:57 GMT",
    "source": "Bloomberg",
    "fetched_at": "2026-06-01T04:49:10.608548"
  },
  {
    "id": "0491fe496b0e",
    "title": "Axios: Trump Wants Changes to Iran Deal, Hormuz Concerns, More",
    "summary": "Source: Bloomberg, 0:00",
    "link": "https://www.bloomberg.com/news/audio/2026-05-31/axios-trump-wants-changes-to-iran-deal-hormuz-concerns-more",
    "published": "Sun, 31 May 2026 10:51:25 GMT",
    "source": "Bloomberg",
    "fetched_at": "2026-06-01T04:49:10.608553"
  },
  {
    "id": "4a0159db25d0",
    "title": "A Strategic Debacle, But Stocks Keep Winning",
    "summary": "<p>A lot is riding on whether inflation from the Iran war can stay manageable.</p>",
    "link": "https://www.bloomberg.com/opinion/newsletters/2026-06-01/a-strategic-debacle-but-stocks-keep-winning",
    "published": "Mon, 01 Jun 2026 04:00:17 GMT",
    "source": "Bloomberg",
    "fetched_at": "2026-06-01T04:49:10.891823"
  },
  {
    "id": "b049f40b73f3",
    "title": "Stocks Hit Record on AI Rally, Oil Rises on Iran: Markets Wrap",
    "summary": "Stocks rose to a record as investors doubled down on the artificial intelligence trade that’s powered equities to all-time highs. Oil climbed as a US-Iran ceasefire deal remained elusive.",
    "link": "https://www.bloomberg.com/news/articles/2026-05-31/oil-climbs-as-us-iran-ceasefire-remains-elusive-markets-wrap",
    "published": "Sun, 31 May 2026 22:10:32 GMT",
    "source": "Bloomberg",
    "fetched_at": "2026-06-01T04:49:10.891835"
  },
  {
    "id": "8b17068acdf3",
    "title": "Copper Gains With US Tariffs Deadline Less Than a Month Away",
    "summary": "Copper advanced in New York and London to kick off a crucial month that should deliver more clarity on the Trump administration’s plans for levies on imports of the metal to the US.",
    "link": "https://www.bloomberg.com/news/articles/2026-06-01/copper-gains-with-us-tariffs-deadline-less-than-a-month-away",
    "published": "Mon, 01 Jun 2026 03:45:02 GMT",
    "source": "Bloomberg",
    "fetched_at": "2026-06-01T04:49:10.891842"
  },
  {
    "id": "2bec021d2943",
    "title": "Aussie Risks More Losses Versus Kiwi on Rate View, Analysts Say",
    "summary": "The Australian dollar may have further scope to fall against the kiwi as traders unwind bearish positions in New Zealand’s currency following a hawkish shift from the nation’s central bank, analysts said.",
    "link": "https://www.bloomberg.com/news/articles/2026-06-01/aussie-risks-more-losses-versus-kiwi-on-rate-view-analysts-say",
    "published": "Mon, 01 Jun 2026 03:32:38 GMT",
    "source": "Bloomberg",
    "fetched_at": "2026-06-01T04:49:10.891848"
  },
  {
    "id": "881f5de9ba52",
    "title": "LG Electronics Shares Jump Over 300% in 2026 on Physical AI Push",
    "summary": "LG Electronics Inc. shares have quadrupled this year as investors applaud the venerable Korean appliance maker’s shift into robotics.",
    "link": "https://www.bloomberg.com/news/articles/2026-06-01/lg-electronics-shares-surge-more-than-300-on-physical-ai-push",
    "published": "Mon, 01 Jun 2026 03:28:28 GMT",
    "source": "Bloomberg",
    "fetched_at": "2026-06-01T04:49:10.891853"
  },
  {
    "id": "62f1567bfb24",
    "title": "India Keeps Local Jet Fuel Prices Unchanged After Airline Plea",
    "summary": "India’s state-owned oil refiners have kept jet fuel prices steady for local flights following a plea from airlines to hold off on further hikes as they grapple with the fallout from the Iran war.",
    "link": "https://www.bloomberg.com/news/articles/2026-06-01/india-keeps-local-jet-fuel-prices-unchanged-after-airline-plea",
    "published": "Mon, 01 Jun 2026 03:27:43 GMT",
    "source": "Bloomberg",
    "fetched_at": "2026-06-01T04:49:10.891858"
  },
  {
    "id": "1802bd19c6af",
    "title": "SMBC Nikko Mulls Launching $627 Million Japan Mezzanine Fund",
    "summary": "SMBC Nikko Securities Inc. is considering establishing a fund with One Investment Management to provide so-called mezzanine financing, people familiar with the matter said.",
    "link": "https://www.bloomberg.com/news/articles/2026-06-01/smbc-nikko-mulls-launching-627-million-japan-mezzanine-fund",
    "published": "Mon, 01 Jun 2026 02:58:08 GMT",
    "source": "Bloomberg",
    "fetched_at": "2026-06-01T04:49:10.891863"
  },
  {
    "id": "62a21c22372e",
    "title": "Korea Boosts Bond-Market Vigil Via Daily Phone Calls, Group Chat",
    "summary": "South Korea intensified monitoring of the government bond market through daily phone calls and a private messaging group with market participants, as authorities step up efforts to contain rising yields.",
    "link": "https://www.bloomberg.com/news/articles/2026-06-01/krw-usd-korea-boosts-bond-market-vigil-via-daily-phone-calls-group-chat",
    "published": "Mon, 01 Jun 2026 02:55:15 GMT",
    "source": "Bloomberg",
    "fetched_at": "2026-06-01T04:49:10.891869"
  },
  {
    "id": "61257ba86b0e",
    "title": "SpaceX’s IPO Forces Wall Street to Reorganize Around It",
    "summary": "<p>The company’s ambitious listing plan is set to clear the way for other mega-offerings. It also risks threatening the integrity of the market itself</p>",
    "link": "https://www.bloomberg.com/news/features/2026-05-31/spacex-s-ipo-led-by-elon-musk-forces-index-funds-and-retail-to-change-the-rules",
    "published": "Sun, 31 May 2026 21:00:09 GMT",
    "source": "Bloomberg",
    "fetched_at": "2026-06-01T04:49:10.891875"
  },
  {
    "id": "bebd0c14400c",
    "title": "ECB’s Schnabel Sees Risk of Unanchored Inflation Views From War",
    "summary": "The European Central Bank can no longer look through the inflationary impact of the war in Iran as price pressures spread beyond energy and the risk of unanchored inflation expectations rises, according to Executive Board member Isabel Schnabel.",
    "link": "https://www.bloomberg.com/news/articles/2026-06-01/ecb-s-schnabel-sees-risk-of-unanchored-inflation-views-from-war",
    "published": "Mon, 01 Jun 2026 02:47:09 GMT",
    "source": "Bloomberg",
    "fetched_at": "2026-06-01T04:49:10.891880"
  },
  {
    "id": "a88dc5187948",
    "title": "Yen Defies Record Intervention as Wait for BOJ Hike Raises Risks",
    "summary": "Yen traders face a heightened risk of intervention over the next two weeks after Japan’s currency defied historic attempts to prop it up.",
    "link": "https://www.bloomberg.com/news/articles/2026-06-01/yen-defies-record-intervention-as-wait-for-boj-hike-raises-risks",
    "published": "Mon, 01 Jun 2026 02:18:48 GMT",
    "source": "Bloomberg",
    "fetched_at": "2026-06-01T04:49:10.891895"
  },
  {
    "id": "f30518fb6fb1",
    "title": "Ryan Is Said to Agree to Buy Nordic Tax Adviser Svalner Atlas",
    "summary": "Ryan LLC, backed by Neuberger and Onex Corp., has agreed to acquire European tax adviser Svalner Atlas Advisors, according to people familiar with the matter.",
    "link": "https://www.bloomberg.com/news/articles/2026-06-01/ryan-is-said-to-agree-to-buy-nordic-tax-adviser-svalner-atlas",
    "published": "Mon, 01 Jun 2026 02:11:41 GMT",
    "source": "Bloomberg",
    "fetched_at": "2026-06-01T04:49:10.891900"
  },
  {
    "id": "2ac41122cee6",
    "title": "Oil Rises From Six-Week Low Amid Uncertainty Over US-Iran Deal",
    "summary": "Oil rose from a six-week low amid uncertainty over the outlook for a peace deal to end the war in Iran.",
    "link": "https://www.bloomberg.com/news/articles/2026-05-31/latest-oil-market-news-and-analysis-for-june-1",
    "published": "Sun, 31 May 2026 22:02:15 GMT",
    "source": "Bloomberg",
    "fetched_at": "2026-06-01T04:49:10.891905"
  },
  {
    "id": "26318e25fd0e",
    "title": "Goldman Sees Two-Sided Risk to Oil as Lower Use Offsets Iran War",
    "summary": "Goldman Sachs Group Inc. sees two-sided risks to oil prices as a slump in demand competes with supply losses from the Middle East because of the Iran war.",
    "link": "https://www.bloomberg.com/news/articles/2026-06-01/goldman-sees-two-sided-risk-to-oil-as-lower-use-offsets-iran-war",
    "published": "Mon, 01 Jun 2026 01:57:36 GMT",
    "source": "Bloomberg",
    "fetched_at": "2026-06-01T04:49:10.891910"
  },
  {
    "id": "583e9ee149f6",
    "title": "India Rate Risks, Fiscal Worries Add to Pressure on Bond Yields",
    "summary": "The recent surge in Indian bond yields may extend as investors weigh prospects of interest-rate hikes, while concerns grow over the government’s fiscal position.",
    "link": "https://www.bloomberg.com/news/articles/2026-06-01/india-rate-risks-fiscal-worries-add-to-pressure-on-bond-yields",
    "published": "Mon, 01 Jun 2026 01:00:00 GMT",
    "source": "Bloomberg",
    "fetched_at": "2026-06-01T04:49:10.891915"
  },
  {
    "id": "294d5a8db08a",
    "title": "Key Takeaways From the Shangri-La Dialogue Forum",
    "summary": "US Defense Secretary Pete Hegseth praised defense allies in Asia and hailed newly stable ties with China at an Asia security forum in Singapore. Key US allies in the region also spoke about the security impact of geopolitical tensions both in Asia-Pacific and the Middle East. Bloomberg's China Correspondent Minmin Low breaks down the latest. (Source: Bloomberg)",
    "link": "https://www.bloomberg.com/news/videos/2026-06-01/key-takeaways-from-the-shangri-la-dialogue-forum-video",
    "published": "Mon, 01 Jun 2026 00:57:45 GMT",
    "source": "Bloomberg",
    "fetched_at": "2026-06-01T04:49:10.891919"
  },
  {
    "id": "ef148c766ce4",
    "title": "China Investors Turn Sellers of Hong Kong Stocks in Rare Reversal",
    "summary": "Chinese mainland investors turned net sellers of Hong Kong stocks for the first time in nearly three years in May, after a surge in tech shares trading onshore eroded the appeal of the city’s market.",
    "link": "https://www.bloomberg.com/news/articles/2026-06-01/china-investors-turn-sellers-of-hk-stocks-in-rare-reversal",
    "published": "Mon, 01 Jun 2026 00:12:56 GMT",
    "source": "Bloomberg",
    "fetched_at": "2026-06-01T04:49:10.891924"
  },
  {
    "id": "7c6255727dc0",
    "title": "Vietnam’s Gene Solutions Eyes Hong Kong IPO to Fund Expansion",
    "summary": "Vietnamese diagnostic testing startup Gene Solutions is preparing for a Hong Kong initial public offering as early as the second quarter of next year, a rare local firm seeking to access deeper capital markets and boost international visibility.",
    "link": "https://www.bloomberg.com/news/articles/2026-06-01/vietnam-genetic-testing-startup-eyes-hong-kong-ipo-to-fund-global-growth",
    "published": "Mon, 01 Jun 2026 00:00:00 GMT",
    "source": "Bloomberg",
    "fetched_at": "2026-06-01T04:49:10.891934"
  },
  {
    "id": "f8528cca08ee",
    "title": "TSMC’s Local Investors Narrow Valuation Gap With Wall Street",
    "summary": "Local investors are driving the premium on Taiwan Semiconductor Manufacturing Co.’s US-listed shares to a two-year low as they pile into the chipmaker’s stock in Taipei on bets the AI boom has further to run.",
    "link": "https://www.bloomberg.com/news/articles/2026-05-31/tsmc-s-local-investors-narrow-valuation-gap-with-wall-street",
    "published": "Sun, 31 May 2026 23:53:02 GMT",
    "source": "Bloomberg",
    "fetched_at": "2026-06-01T04:49:10.891939"
  },
  {
    "id": "bdafe87c771f",
    "title": "China’s Shoppers Are Buying Luxury Again as Stock Market Rebounds",
    "summary": "Chinese consumers are showing signs of a renewed appetite for high-end beauty and fashion products, a rare bright spot for global luxury brands after years of weak demand and margin-eroding discounts in their most important growth market.",
    "link": "https://www.bloomberg.com/news/articles/2026-05-31/china-s-shoppers-are-buying-luxury-again-as-stock-market-rebounds",
    "published": "Sun, 31 May 2026 23:00:00 GMT",
    "source": "Bloomberg",
    "fetched_at": "2026-06-01T04:49:10.891944"
  },
  {
    "id": "4b8cec322a6c",
    "title": "Wall Street Risk Rally Powers Past War Stalemate",
    "summary": "Three months into the Iran war, it has become all but impossible to damp the bullish spirit driving global markets for risky assets.",
    "link": "https://www.bloomberg.com/news/articles/2026-05-31/wall-street-risk-rally-powers-past-war-stalemate-markets-wrap",
    "published": "Sun, 31 May 2026 19:29:04 GMT",
    "source": "Bloomberg",
    "fetched_at": "2026-06-01T04:49:10.891954"
  },
  {
    "id": "8841d5f61838",
    "title": "Billionaire Hotelier Wants to Take Japan’s APA Global",
    "summary": "The family-run APA hotel chain that turned efficiency into a hospitality empire is betting it can export its uniquely Japanese formula abroad, starting with North America. APA Group CEO Isshi Motoya spoke with Bloomberg News' Momoka Yokoyama in Tokyo. (Source: Bloomberg)",
    "link": "https://www.bloomberg.com/news/videos/2026-05-31/billionaire-hotelier-wants-to-take-japan-s-apa-global-video",
    "published": "Sun, 31 May 2026 21:00:10 GMT",
    "source": "Bloomberg",
    "fetched_at": "2026-06-01T04:49:10.891958"
  },
  {
    "id": "19bc038bacc3",
    "title": "Bond Trader Bets on Fed Hike Poised for Gut Check From Jobs Data",
    "summary": "Bond traders are looking to a key jobs report this week to confirm their wagers that the US economy is strong enough to push the Federal Reserve to lift interest rates by next year.",
    "link": "https://www.bloomberg.com/news/articles/2026-05-31/bond-trader-bets-on-fed-hike-poised-for-gut-check-from-jobs-data",
    "published": "Sun, 31 May 2026 19:00:00 GMT",
    "source": "Bloomberg",
    "fetched_at": "2026-06-01T04:49:10.891968"
  },
  {
    "id": "df8db76bb021",
    "title": "IMF Chief, Venezuelan Officials Hold Talks on Economy Issues",
    "summary": "International Monetary Fund Managing Director Kristalina Georgieva and Venezuelan economic official Calixto Ortega held talks in Washington, the IMF head’s first in-person meeting with country’s authorities since the fund resumed formal engagement with Venezuela last month.",
    "link": "https://www.bloomberg.com/news/articles/2026-05-30/imf-chief-venezuelan-officials-hold-talks-on-economic-stability",
    "published": "Sat, 30 May 2026 21:59:53 GMT",
    "source": "Bloomberg",
    "fetched_at": "2026-06-01T04:49:10.891973"
  },
  {
    "id": "ec963d409c15",
    "title": "Bloomberg This Weekend 5/31/2026",
    "summary": "The news doesn’t stop when markets close. Hosts David Gura, Christina Ruffini and Lisa Mateo bring clarity, context and a bit of humor to the weekend’s biggest headlines, LIVE from New York. Joined by New York Times Chief Africa Correspondent Declan Walsh, Harvard Kennedy School Center for Public Leadership Research Fellow Gautam Mukunda, Can’t Look Away Director Matthew O’Neill and Fmr. National Security Advisor & Fmr. US Ambassador to the UN Amb. John Bolton. (Source: Bloomberg)",
    "link": "https://www.bloomberg.com/news/videos/2026-05-31/bloomberg-this-weekend-5-31-2026-video",
    "published": "Sun, 31 May 2026 17:07:18 GMT",
    "source": "Bloomberg",
    "fetched_at": "2026-06-01T04:49:10.891978"
  }
]