[
  {
    "id": "5f47179e2e53",
    "title": "India’s Zee Seeks Shareholder Trust, Former Glory With Fundraise",
    "summary": "As rivals splurge on content and distribution, Zee will need to keep pace.",
    "link": "https://www.bloomberg.com/news/newsletters/2026-06-16/india-s-zee-seeks-shareholder-trust-with-240-million-fundraise",
    "published": "Tue, 16 Jun 2026 11:35:08 GMT",
    "source": "Bloomberg",
    "fetched_at": "2026-06-16T11:35:58.227307"
  },
  {
    "id": "e6c305043434",
    "title": "Trump at Odds With Allies Over Details of Hormuz Deal",
    "summary": "Here’s what you need to know to start your day",
    "link": "https://www.bloomberg.com/news/newsletters/2026-06-16/trump-at-odds-with-allies-over-details-of-hormuz-deal",
    "published": "Tue, 16 Jun 2026 11:18:41 GMT",
    "source": "Bloomberg",
    "fetched_at": "2026-06-16T11:35:58.227322"
  },
  {
    "id": "c12d75238272",
    "title": "Stock Movers: SpaceX, Novo Nordisk, Dave & Busters (Podcast)",
    "summary": "Source: Bloomberg, 0:00",
    "link": "https://www.bloomberg.com/news/audio/2026-06-16/stock-movers-spacex-novo-nordisk-dave-busters-podcast",
    "published": "Tue, 16 Jun 2026 11:09:00 GMT",
    "source": "Bloomberg",
    "fetched_at": "2026-06-16T11:35:58.227328"
  },
  {
    "id": "334702d276e0",
    "title": "US and Iran Prepare for Deal Signing, SpaceX Soars, More",
    "summary": "Source: Bloomberg, 6:17",
    "link": "https://www.bloomberg.com/news/audio/2026-06-16/us-and-iran-prepare-for-deal-signing-spacex-soars-more",
    "published": "Tue, 16 Jun 2026 10:22:27 GMT",
    "source": "Bloomberg",
    "fetched_at": "2026-06-16T11:35:58.227334"
  },
  {
    "id": "d14f4689e76b",
    "title": "Bloomberg Daybreak: US at Odds With Allies (Podcast)",
    "summary": "Source: Bloomberg, 15:50",
    "link": "https://www.bloomberg.com/news/audio/2026-06-16/bloomberg-daybreak-us-at-odds-with-allies-podcast",
    "published": "Tue, 16 Jun 2026 09:40:52 GMT",
    "source": "Bloomberg",
    "fetched_at": "2026-06-16T11:35:58.227340"
  },
  {
    "id": "0eed405b2df7",
    "title": "China’s Retail Sales Fall for First Time Since the Pandemic",
    "summary": "Get caught up.",
    "link": "https://www.bloomberg.com/news/newsletters/2026-06-16/china-s-retail-sales-fall-for-first-time-since-covid-in-new-worry-for-economy",
    "published": "Tue, 16 Jun 2026 09:35:22 GMT",
    "source": "Bloomberg",
    "fetched_at": "2026-06-16T11:35:58.227345"
  },
  {
    "id": "70003e97bf7b",
    "title": "Stock Movers: Rathbones, STMicro, Porsche (Podcast)",
    "summary": "Source: Bloomberg, 4:08",
    "link": "https://www.bloomberg.com/news/audio/2026-06-16/stock-movers-rathbones-stmicro-porsche-podcast",
    "published": "Tue, 16 Jun 2026 09:32:26 GMT",
    "source": "Bloomberg",
    "fetched_at": "2026-06-16T11:35:58.227351"
  },
  {
    "id": "197c5503694e",
    "title": "US at Odds With Allies on Hormuz, SpaceX Stock Jumps Again, More",
    "summary": "Source: Bloomberg, 0:00",
    "link": "https://www.bloomberg.com/news/audio/2026-06-16/us-at-odds-with-allies-on-hormuz-spacex-stock-jumps-again-more",
    "published": "Tue, 16 Jun 2026 09:29:48 GMT",
    "source": "Bloomberg",
    "fetched_at": "2026-06-16T11:35:58.227360"
  },
  {
    "id": "97d94cc7fb65",
    "title": "US & Allies Hormuz Split, Fresh Russia Sanctions, More",
    "summary": "Source: Bloomberg, 0:00",
    "link": "https://www.bloomberg.com/news/audio/2026-06-16/us-allies-hormuz-split-fresh-russia-sanctions-more",
    "published": "Tue, 16 Jun 2026 08:45:54 GMT",
    "source": "Bloomberg",
    "fetched_at": "2026-06-16T11:35:58.227367"
  },
  {
    "id": "2ee7216ff0ab",
    "title": "Stock Movers: Unicredit, Rathbones, Rheinmetall (Podcast)",
    "summary": "Source: Bloomberg, 4:26",
    "link": "https://www.bloomberg.com/news/audio/2026-06-16/stock-movers-unicredit-rathbones-rheinmetall-podcast",
    "published": "Tue, 16 Jun 2026 08:15:00 GMT",
    "source": "Bloomberg",
    "fetched_at": "2026-06-16T11:35:58.227398"
  },
  {
    "id": "395a79e67b85",
    "title": "US at Odds With Allies on Hormuz, China Economy Stalls, More",
    "summary": "Source: Bloomberg, 0:00",
    "link": "https://www.bloomberg.com/news/audio/2026-06-16/us-at-odds-with-allies-on-hormuz-china-economy-stalls-more",
    "published": "Tue, 16 Jun 2026 07:42:38 GMT",
    "source": "Bloomberg",
    "fetched_at": "2026-06-16T11:35:58.227405"
  },
  {
    "id": "e4a4dd6ffeaf",
    "title": "Thames Water Nears Nationalisation As Minister Warns Rescue Deal Not Enough",
    "summary": "Thames Water nears temporary nationalisation; Rathbones pauses some onboarding",
    "link": "https://www.bloomberg.com/news/newsletters/2026-06-16/thames-water-nears-temporary-nationalisation-as-uk-minister-doubts-rescue-deal",
    "published": "Tue, 16 Jun 2026 07:20:28 GMT",
    "source": "Bloomberg",
    "fetched_at": "2026-06-16T11:35:58.227410"
  },
  {
    "id": "10bcea5b3b17",
    "title": "India’s Pharma Billionaire Eyes Crown of World’s Top Insulin Supplier",
    "summary": "Indian drugmaker Biocon Ltd. is aiming to become the world’s top supplier of insulin in the coming years, its co-founder Kiran Mazumdar-Shaw said, by capturing growing demand for the critical drug while Big Pharma shifts its focus to other medicines.",
    "link": "https://www.bloomberg.com/news/articles/2026-06-16/pharma-billionaire-eyes-crown-of-world-s-top-insulin-supplier",
    "published": "Tue, 16 Jun 2026 07:11:26 GMT",
    "source": "Bloomberg",
    "fetched_at": "2026-06-16T11:35:58.227416"
  },
  {
    "id": "35d8fb989e7b",
    "title": "US & Allies Split on Hormuz, BOJ Rate Hike, More",
    "summary": "Source: Bloomberg, 0:00",
    "link": "https://www.bloomberg.com/news/audio/2026-06-16/us-allies-split-on-hormuz-boj-rate-hike-more",
    "published": "Tue, 16 Jun 2026 06:53:56 GMT",
    "source": "Bloomberg",
    "fetched_at": "2026-06-16T11:35:58.227421"
  },
  {
    "id": "95ae84bd1917",
    "title": "The US Is at Odds With European Allies Over the State of the Iran War",
    "summary": "Get caught up.",
    "link": "https://www.bloomberg.com/news/newsletters/2026-06-16/the-us-is-at-odds-with-european-allies-over-the-state-of-the-iran-war",
    "published": "Tue, 16 Jun 2026 06:12:20 GMT",
    "source": "Bloomberg",
    "fetched_at": "2026-06-16T11:35:58.227427"
  },
  {
    "id": "53edce5ad9f7",
    "title": "Bloomberg Daybreak Europe: Hormuz Reality Check (Podcast)",
    "summary": "Source: Bloomberg, 0:00",
    "link": "https://www.bloomberg.com/news/audio/2026-06-16/bloomberg-daybreak-europe-hormuz-reality-check-podcast",
    "published": "Tue, 16 Jun 2026 05:51:31 GMT",
    "source": "Bloomberg",
    "fetched_at": "2026-06-16T11:35:58.227432"
  },
  {
    "id": "e73933773a5a",
    "title": "Europe’s Hormuz Doubts, Fatal B-52 Bomber Crash",
    "summary": "Source: Bloomberg, 7:58",
    "link": "https://www.bloomberg.com/news/audio/2026-06-16/europe-s-hormuz-doubts-fatal-b-52-bomber-crash",
    "published": "Tue, 16 Jun 2026 05:48:51 GMT",
    "source": "Bloomberg",
    "fetched_at": "2026-06-16T11:35:58.227437"
  },
  {
    "id": "6e22639e3881",
    "title": "Bloomberg Law: Weaponization Fund & SBF's Appeal Fails (Podcast)",
    "summary": "Source: Bloomberg, 28:21",
    "link": "https://www.bloomberg.com/news/audio/2026-06-16/bloomberg-law-weaponization-fund-sbf-s-appeal-fails-podcast",
    "published": "Tue, 16 Jun 2026 03:25:19 GMT",
    "source": "Bloomberg",
    "fetched_at": "2026-06-16T11:35:58.227442"
  },
  {
    "id": "4d4cbf423e16",
    "title": "Trump: Hormuz to Open Friday, B-52 Bomber Crash, More",
    "summary": "Source: Bloomberg, 6:40",
    "link": "https://www.bloomberg.com/news/audio/2026-06-16/trump-hormuz-to-open-friday-b-52-bomber-crash-more",
    "published": "Tue, 16 Jun 2026 03:23:23 GMT",
    "source": "Bloomberg",
    "fetched_at": "2026-06-16T11:35:58.227447"
  },
  {
    "id": "d6e37a92a63c",
    "title": "China Home Prices Fall at Faster Pace in Setback to Revival",
    "summary": "China’s home prices fell at a quicker pace in May, halting green shoots seen at the start of the year that had raised hopes of a recovery.",
    "link": "https://www.bloomberg.com/news/articles/2026-06-16/china-home-prices-fall-at-faster-pace-in-setback-to-revival",
    "published": "Tue, 16 Jun 2026 01:37:01 GMT",
    "source": "Bloomberg",
    "fetched_at": "2026-06-16T11:35:58.227452"
  },
  {
    "id": "3954d68c2068",
    "title": "Global Funds Pile Into India Bonds as Oil Cools",
    "summary": "Lower crude prices improves inflation outlook and eases pressure on current account deficit.",
    "link": "https://www.bloomberg.com/news/newsletters/2026-06-16/foreign-inflows-into-india-bonds-at-15-month-high-as-oil-cools-on-peace-deal",
    "published": "Tue, 16 Jun 2026 02:47:48 GMT",
    "source": "Bloomberg",
    "fetched_at": "2026-06-16T11:35:58.227457"
  },
  {
    "id": "08b4c87c3b5e",
    "title": "Trump Hormuz Optimism, Eight Dead in B-52 Bomber Crash, More",
    "summary": "Source: Bloomberg, 6:40",
    "link": "https://www.bloomberg.com/news/audio/2026-06-16/trump-hormuz-optimism-eight-dead-in-b-52-bomber-crash-more",
    "published": "Tue, 16 Jun 2026 02:34:51 GMT",
    "source": "Bloomberg",
    "fetched_at": "2026-06-16T11:35:58.227462"
  },
  {
    "id": "cf6a12d50901",
    "title": "Bloomberg Daybreak Asia: US-Iran Deal Reaction (Podcast)",
    "summary": "Source: Bloomberg, 0:00",
    "link": "https://www.bloomberg.com/news/audio/2026-06-16/bloomberg-daybreak-asia-us-iran-deal-reaction-podcast",
    "published": "Tue, 16 Jun 2026 02:20:27 GMT",
    "source": "Bloomberg",
    "fetched_at": "2026-06-16T11:35:58.227471"
  },
  {
    "id": "6e85ffeb0b70",
    "title": "Trump Optimistic on Hormuz Reopening, B-52 Crash in California",
    "summary": "Source: Bloomberg, 6:40",
    "link": "https://www.bloomberg.com/news/audio/2026-06-16/trump-optimistic-on-hormuz-reopening-b-52-crash-in-california",
    "published": "Tue, 16 Jun 2026 01:47:35 GMT",
    "source": "Bloomberg",
    "fetched_at": "2026-06-16T11:35:58.227476"
  },
  {
    "id": "1ad0cde17241",
    "title": "Trump: Hormuz to Open Friday, B-52 Crash at CA Base, More",
    "summary": "Source: Bloomberg, 6:40",
    "link": "https://www.bloomberg.com/news/audio/2026-06-16/trump-hormuz-to-open-friday-b-52-crash-at-ca-base-more",
    "published": "Tue, 16 Jun 2026 00:49:17 GMT",
    "source": "Bloomberg",
    "fetched_at": "2026-06-16T11:35:58.227480"
  },
  {
    "id": "15a0f38b6e71",
    "title": "Trump Says Hormuz to Reopen, B-52 Bomber Crash, More",
    "summary": "Source: Bloomberg, 6:40",
    "link": "https://www.bloomberg.com/news/audio/2026-06-15/trump-says-hormuz-to-reopen-b-52-bomber-crash-more",
    "published": "Mon, 15 Jun 2026 23:58:19 GMT",
    "source": "Bloomberg",
    "fetched_at": "2026-06-16T11:35:58.227485"
  },
  {
    "id": "f4e63093858b",
    "title": "SpaceX Investors at US Retail Brokers Got at Least One IPO Share",
    "summary": "Customers at some of the largest retail brokerage firms in the US each received at least a single share in SpaceX’s $86.2 billion IPO, underscoring how the offering was designed to give individual investors a sizable role.",
    "link": "https://www.bloomberg.com/news/articles/2026-06-15/spacex-investors-at-us-retail-brokers-got-at-least-one-ipo-share",
    "published": "Mon, 15 Jun 2026 23:52:01 GMT",
    "source": "Bloomberg",
    "fetched_at": "2026-06-16T11:35:58.227490"
  },
  {
    "id": "d0486be7bda9",
    "title": "Trump Hails Iran Deal, B-52 Bomber Crashes in California, More",
    "summary": "Source: Bloomberg, 6:29",
    "link": "https://www.bloomberg.com/news/audio/2026-06-15/trump-hails-iran-deal-b-52-bomber-crashes-in-california-more",
    "published": "Mon, 15 Jun 2026 23:07:28 GMT",
    "source": "Bloomberg",
    "fetched_at": "2026-06-16T11:35:58.227495"
  },
  {
    "id": "4eb30f33a3d2",
    "title": "Gina Rinehart’s SpaceX Investment, KPMG Pauses Government Bids",
    "summary": "Get caught up.",
    "link": "https://www.bloomberg.com/news/newsletters/2026-06-15/gina-rinehart-buys-spacex-kpmg-to-pause-government-contract-bids",
    "published": "Mon, 15 Jun 2026 22:47:39 GMT",
    "source": "Bloomberg",
    "fetched_at": "2026-06-16T11:35:58.227500"
  },
  {
    "id": "8afcf640de96",
    "title": "Trump Insists Hormuz Will Open Friday, B-52 Bomber Crash, More",
    "summary": "Source: Bloomberg, 6:19",
    "link": "https://www.bloomberg.com/news/audio/2026-06-15/trump-insists-hormuz-will-open-friday-b-52-bomber-crash-more",
    "published": "Mon, 15 Jun 2026 22:17:06 GMT",
    "source": "Bloomberg",
    "fetched_at": "2026-06-16T11:35:58.227505"
  },
  {
    "id": "05e4766a84d2",
    "title": "SpaceX Set to Overtake Amazon in Value as It Soars for Third Day",
    "summary": "SpaceX shares surged in premarket trading, putting the firm on track to overtake Amazon.com Inc. as the fifth largest publicly traded company in the world just days after its blockbuster debut.",
    "link": "https://www.bloomberg.com/news/articles/2026-06-16/spacex-spcx-stock-set-for-more-than-50-jump-in-just-three-sessions",
    "published": "Tue, 16 Jun 2026 08:09:12 GMT",
    "source": "Bloomberg",
    "fetched_at": "2026-06-16T11:35:58.325282"
  },
  {
    "id": "ba64ca2f4c67",
    "title": "Stocks Drift After Three-Day Rally; SpaceX Surges: Markets Wrap",
    "summary": "US stocks paused after a three-day rally with investors shifting their focus to a raft of central bank decisions this week. SpaceX continued to surge, on track for a more than 50% jump since going public.",
    "link": "https://www.bloomberg.com/news/articles/2026-06-15/oil-holds-losses-after-iran-deal-spurs-stock-rally-markets-wrap",
    "published": "Mon, 15 Jun 2026 22:06:05 GMT",
    "source": "Bloomberg",
    "fetched_at": "2026-06-16T11:35:58.325293"
  },
  {
    "id": "ce7044b1258f",
    "title": "Nike Can’t Afford to Lose This World Cup",
    "summary": "Nike has the star power and home advantage. But with its turnaround moving slowly, the World Cup may matter more to Nike than Adidas, explains Bloomberg Opinion columnist Andrea Felsted. (Source: Bloomberg)",
    "link": "https://www.bloomberg.com/news/videos/2026-06-16/opinion-nike-can-t-afford-to-lose-this-world-cup-video",
    "published": "Tue, 16 Jun 2026 11:19:57 GMT",
    "source": "Bloomberg",
    "fetched_at": "2026-06-16T11:35:58.325299"
  },
  {
    "id": "12420d9d6fc0",
    "title": "Hormuz Reopening Seen Unleashing Pent-Up Gulf Grain Demand",
    "summary": "An interim US-Iran deal to end their months-long war and potentially fully reopen the Strait of Hormuz is likely to trigger a rush of grain imports to nations in the Persian Gulf after months of reliance on longer, less efficient routes.",
    "link": "https://www.bloomberg.com/news/articles/2026-06-16/hormuz-reopening-seen-unleashing-pent-up-gulf-grain-demand",
    "published": "Tue, 16 Jun 2026 11:12:16 GMT",
    "source": "Bloomberg",
    "fetched_at": "2026-06-16T11:35:58.325305"
  },
  {
    "id": "361f788a2d60",
    "title": "Bondholders Forced to Reckon With $4 Billion Tax Threat in Bitter Credit Feud",
    "summary": "Patrick Drahi was running out of options to save his debt-ridden telecom empire.",
    "link": "https://www.bloomberg.com/news/articles/2026-06-16/bondholders-forced-to-reckon-with-4-billion-tax-threat-in-bitter-credit-feud",
    "published": "Tue, 16 Jun 2026 11:12:11 GMT",
    "source": "Bloomberg",
    "fetched_at": "2026-06-16T11:35:58.325311"
  },
  {
    "id": "2e862b9d46a3",
    "title": "1MDB Theft Made Attila the Hun Look Like ‘Choirboy,’ Judge Says",
    "summary": "The judge who convicted former Malaysian Prime Minister Najib Razak over the 1MDB scandal said the plunder of the sovereign wealth fund was so vast that it eclipsed the exploits of Attila the Hun, one of history’s most notorious conquerors.",
    "link": "https://www.bloomberg.com/news/articles/2026-06-16/1mdb-theft-made-attila-the-hun-look-like-choirboy-judge-says",
    "published": "Tue, 16 Jun 2026 11:07:28 GMT",
    "source": "Bloomberg",
    "fetched_at": "2026-06-16T11:35:58.325316"
  },
  {
    "id": "716ce8183846",
    "title": "Dolce &amp; Gabbana Weighs Sale of Milan Properties to Raise Cash",
    "summary": "Dolce &amp; Gabbana is negotiating with lenders over the potential sale of real estate assets in Milan as part of an effort to raise liquidity and refinance debt, according to people familiar with the matter.",
    "link": "https://www.bloomberg.com/news/articles/2026-06-16/dolce-gabbana-weighs-sale-of-milan-properties-to-raise-cash",
    "published": "Tue, 16 Jun 2026 11:03:50 GMT",
    "source": "Bloomberg",
    "fetched_at": "2026-06-16T11:35:58.325321"
  },
  {
    "id": "778ddd69aefa",
    "title": "Middle East Oil Collapses as Contango Returns on Supply Hope",
    "summary": "Middle Eastern crude markets have collapsed, as the US-Iran agreement to reopen the Strait of Hormuz spurs optimism around an increase in flows from the oil-rich region.",
    "link": "https://www.bloomberg.com/news/articles/2026-06-16/middle-east-oil-markets-weaken-on-optimism-over-increased-supply",
    "published": "Tue, 16 Jun 2026 02:55:45 GMT",
    "source": "Bloomberg",
    "fetched_at": "2026-06-16T11:35:58.325326"
  },
  {
    "id": "8021ed24ec07",
    "title": "Verizon Debuts New Plan, Loyalty Program in Battle for Customers",
    "summary": "The freebies competition is heating up among US wireless carriers.",
    "link": "https://www.bloomberg.com/news/articles/2026-06-16/verizon-debuts-new-plan-loyalty-program-in-battle-for-customers",
    "published": "Tue, 16 Jun 2026 11:00:00 GMT",
    "source": "Bloomberg",
    "fetched_at": "2026-06-16T11:35:58.325331"
  },
  {
    "id": "5b789bfce166",
    "title": "Qatar Plans to Rapidly Restart LNG Output After Hormuz Opens",
    "summary": "Qatar is planning to rapidly boost liquefied natural gas production once the Strait of Hormuz reopens, aiming to restore most of its export capacity within two months, according to people familiar with the matter.",
    "link": "https://www.bloomberg.com/news/articles/2026-06-16/qatar-plans-to-rapidly-restart-lng-production-after-hormuz-opens",
    "published": "Tue, 16 Jun 2026 07:11:46 GMT",
    "source": "Bloomberg",
    "fetched_at": "2026-06-16T11:35:58.325336"
  },
  {
    "id": "eaeec2dd1fee",
    "title": "Biocon's Mazumdar-Shaw Says Firm On Track To Be Top Insulin Maker",
    "summary": "Biocon Executive Chairperson Kiran Mazumdar-Shaw says she is confident that the company's investment and capacity expansion in Insulin will make the company the top hub for the drug in the next five years. She speaks in an exclusive conversation with Bloomberg's Haslinda Amin. (Source: Bloomberg)",
    "link": "https://www.bloomberg.com/news/videos/2026-06-16/founder-biocon-aiming-to-become-top-insulin-maker-video",
    "published": "Tue, 16 Jun 2026 01:40:53 GMT",
    "source": "Bloomberg",
    "fetched_at": "2026-06-16T11:35:58.325341"
  },
  {
    "id": "7602e549db74",
    "title": "Empty Tankers Entering Gulf Via Hormuz Are Key for Energy Market",
    "summary": "The transit of empty ships through the Strait of Hormuz into the energy-rich Persian Gulf is being eagerly watched by the market, which would indicate increasing confidence in the outlook for a sustained peace deal.",
    "link": "https://www.bloomberg.com/news/articles/2026-06-16/empty-tankers-entering-gulf-via-hormuz-is-key-for-energy-market",
    "published": "Tue, 16 Jun 2026 10:46:29 GMT",
    "source": "Bloomberg",
    "fetched_at": "2026-06-16T11:35:58.325347"
  },
  {
    "id": "93e0780e4fe3",
    "title": "EBA Eyes Bigger Role for Banks in Setting Key Capital Buffer",
    "summary": "Europe’s top banking regulator said watchdogs should rely more on banks to calculate how big of a safety cushion they need on top of their minimum capital requirements.",
    "link": "https://www.bloomberg.com/news/articles/2026-06-16/eba-eyes-bigger-role-for-banks-in-setting-key-capital-buffer",
    "published": "Tue, 16 Jun 2026 10:44:22 GMT",
    "source": "Bloomberg",
    "fetched_at": "2026-06-16T11:35:58.325351"
  },
  {
    "id": "20e9ea68cb03",
    "title": "SpaceX Shares Surge, US & Iran Prepare for Deal Signing | The Opening Trade 6/16/2026",
    "summary": "The US and Iran are preparing to formally sign their interim peace deal in Switzerland on Friday, with both sides claiming victory and oil traders and shippers unsure over how quickly the Strait of Hormuz will be reopened.\n\nSpaceX shares surged in premarket trading, putting the stock on track to extend a rally following its blockbuster debut last week.\n\nThe Opening Trade has everything you need to know as markets open across Europe. With analysis you won't find anywhere else, we break down the biggest stories of the day and speak to top guests who have skin in the game. Hosted by Anna Edwards, Guy Johnson and Tom Mackenzie. (Source: Bloomberg)",
    "link": "https://www.bloomberg.com/news/videos/2026-06-16/the-opening-trade-6-16-2026-video",
    "published": "Tue, 16 Jun 2026 10:43:07 GMT",
    "source": "Bloomberg",
    "fetched_at": "2026-06-16T11:35:58.325357"
  },
  {
    "id": "ba6ca9f9fd8b",
    "title": "The Prospect of a Quieter Fed Could Roil Bond Prices",
    "summary": "Warsh has hinted at less communication from THE central bank.",
    "link": "https://www.bloomberg.com/news/newsletters/2026-06-16/the-prospect-of-a-quieter-fed-could-roil-bond-prices",
    "published": "Tue, 16 Jun 2026 10:35:14 GMT",
    "source": "Bloomberg",
    "fetched_at": "2026-06-16T11:35:58.325361"
  },
  {
    "id": "6d283f260c50",
    "title": "SBI Plans Indian Rupee Deposits in Sri Lanka to Support Trade",
    "summary": "State Bank of India is planning to introduce Indian rupee-denominated deposits in Sri Lanka, a move aimed at encouraging wider use of the currency in trade and investment between the neighboring nations.",
    "link": "https://www.bloomberg.com/news/articles/2026-06-16/sbi-plans-indian-rupee-deposits-in-sri-lanka-to-support-trade",
    "published": "Tue, 16 Jun 2026 10:34:47 GMT",
    "source": "Bloomberg",
    "fetched_at": "2026-06-16T11:35:58.325366"
  },
  {
    "id": "9a4d7c1bf101",
    "title": "Glencore, Trafigura Said Set to Invest in Merdeka’s HK Listing",
    "summary": "Glencore Plc, Mercuria Energy Group and Trafigura Group are among key investors planning to buy shares in the Hong Kong listing of Indonesian gold miner PT Merdeka Gold Resources, according to people familiar with the matter.",
    "link": "https://www.bloomberg.com/news/articles/2026-06-16/glencore-trafigura-said-set-to-invest-in-merdeka-s-hk-listing",
    "published": "Tue, 16 Jun 2026 10:24:57 GMT",
    "source": "Bloomberg",
    "fetched_at": "2026-06-16T11:35:58.325389"
  },
  {
    "id": "1fc2e16977f4",
    "title": "Don’t Get Overexcited on Oil Price Moderation, AIB’s Hunt Says",
    "summary": "The global economy still faces multiple risks even as the US and Iran agree to halt the war in the Middle East, the head of Irish bank AIB Group Plc warned.",
    "link": "https://www.bloomberg.com/news/articles/2026-06-16/don-t-get-overexcited-on-oil-price-moderation-aib-s-hunt-says",
    "published": "Tue, 16 Jun 2026 10:15:24 GMT",
    "source": "Bloomberg",
    "fetched_at": "2026-06-16T11:35:58.325395"
  },
  {
    "id": "91db377bac0d",
    "title": "Turkey Seeks Higher Oil Flows Via Iraq Pipeline to Renew Deal",
    "summary": "Turkey is seeking higher oil flows through a crucial pipeline that runs through its territory from northern Iraq in order to renew a contract that expires in a little over a month, according to a Turkish official with direct knowledge of the matter.",
    "link": "https://www.bloomberg.com/news/articles/2026-06-16/turkey-seeks-higher-oil-flows-via-iraq-pipeline-to-renew-deal",
    "published": "Tue, 16 Jun 2026 10:00:36 GMT",
    "source": "Bloomberg",
    "fetched_at": "2026-06-16T11:35:58.325400"
  },
  {
    "id": "ff45aaae51b7",
    "title": "Riksbank Rate Seen Steady With Norway on Edge: Decision Guide",
    "summary": "Sweden and Norway face contrasting economic risks, but the two Nordic neighbors are still likely to emerge with the same outcome of no change for borrowing costs this week.",
    "link": "https://www.bloomberg.com/news/articles/2026-06-16/riksbank-rate-seen-steady-with-norway-on-edge-decision-guide",
    "published": "Tue, 16 Jun 2026 10:00:00 GMT",
    "source": "Bloomberg",
    "fetched_at": "2026-06-16T11:35:58.325405"
  },
  {
    "id": "0b07ce3dcb18",
    "title": "Warsh Wants Less Fed Talk, Risking More Market Surprises",
    "summary": "Former Federal Reserve Chair Ben Bernanke famously said monetary policy is 98% talk and only 2% action. Kevin Warsh wants to shake up the mix.",
    "link": "https://www.bloomberg.com/news/articles/2026-06-16/warsh-wants-less-fed-talk-risking-more-market-surprises",
    "published": "Tue, 16 Jun 2026 10:00:00 GMT",
    "source": "Bloomberg",
    "fetched_at": "2026-06-16T11:35:58.325410"
  },
  {
    "id": "b2093a965d5d",
    "title": "Blackstone Grows Asset-Based Lending With New Unit, Taps Garlick",
    "summary": "Blackstone Inc. rolled out a platform to lend against physical assets like inventory and equipment, as alternative asset managers increasingly muscle into territory long dominated by banks.",
    "link": "https://www.bloomberg.com/news/articles/2026-06-16/blackstone-grows-asset-based-lending-with-new-unit-taps-garlick",
    "published": "Tue, 16 Jun 2026 10:00:00 GMT",
    "source": "Bloomberg",
    "fetched_at": "2026-06-16T11:35:58.325415"
  },
  {
    "id": "c227c0c4ccf0",
    "title": "Reeves Says Her Plans Will Make UK Less Reliant on Bond Markets",
    "summary": "Chancellor of the Exchequer Rachel Reeves said her ambition is to balance the budget in 2029, a more demanding target than her current fiscal rules as she pledged to make Britain less at the mercy of the bond markets.",
    "link": "https://www.bloomberg.com/news/articles/2026-06-16/reeves-says-her-plans-will-make-uk-less-reliant-on-bond-markets",
    "published": "Tue, 16 Jun 2026 09:58:25 GMT",
    "source": "Bloomberg",
    "fetched_at": "2026-06-16T11:35:58.325419"
  },
  {
    "id": "62cc1a474a31",
    "title": "Thames Water Edges Closer to Nationalization With Rescue in Doubt",
    "summary": "Thames Water moved closer to temporary nationalization after a senior government minister said a rescue deal put forward by creditors wasn’t sufficient.",
    "link": "https://www.bloomberg.com/news/articles/2026-06-16/thames-edges-closer-to-nationalization-with-rescue-deal-in-doubt",
    "published": "Tue, 16 Jun 2026 07:19:47 GMT",
    "source": "Bloomberg",
    "fetched_at": "2026-06-16T11:35:58.325424"
  },
  {
    "id": "85492822dafa",
    "title": "German Investor Outlook Jumps With Iran Resolution in Sight",
    "summary": "German investor optimism improved more than anticipated on hopes that a swift end to the Iran war will ease pressure on Europe’s largest economy.",
    "link": "https://www.bloomberg.com/news/articles/2026-06-16/german-investor-outlook-jumps-with-iran-resolution-in-sight",
    "published": "Tue, 16 Jun 2026 09:05:06 GMT",
    "source": "Bloomberg",
    "fetched_at": "2026-06-16T11:35:58.325429"
  },
  {
    "id": "cd74ca27bf40",
    "title": "Jeff Currie Says Hormuz Flows May Not Normalize Until End of the Year",
    "summary": "Jeff Currie, executive co-chairman at Abaxx Markets, says “the uncertainty remains quite high” around the Strait of Hormuz as maintaining the US-Iran ceasefire will be challenging. Currie looks at what the interim agreement means for the global oil market, what’s behind the oil price drop, and how quickly Gulf nations can restore production. (Source: Bloomberg)",
    "link": "https://www.bloomberg.com/news/videos/2026-06-16/currie-hormuz-flows-may-not-normalize-until-year-s-end-video",
    "published": "Tue, 16 Jun 2026 09:38:31 GMT",
    "source": "Bloomberg",
    "fetched_at": "2026-06-16T11:35:58.325434"
  },
  {
    "id": "8ca5ad67eb17",
    "title": "Taiwan Frees Life Insurers to Deploy Capital in AI Projects",
    "summary": "Taiwan is easing regulations to give life insurers flexibility to invest in artificial intelligence projects, part of an ongoing campaign by authorities to redirect a larger slice of the industry’s $1 trillion asset pool back home.",
    "link": "https://www.bloomberg.com/news/articles/2026-06-16/taiwan-frees-life-insurers-to-deploy-capital-in-ai-projects",
    "published": "Tue, 16 Jun 2026 09:35:25 GMT",
    "source": "Bloomberg",
    "fetched_at": "2026-06-16T11:35:58.325439"
  },
  {
    "id": "a4d6d9eb9515",
    "title": "Emerging Stocks Near Record High on Tech Gains, Lower Oil Prices",
    "summary": "Emerging-market stocks climbed for a third day, holding near a record high, as crude prices fell further and the tech rally extended.",
    "link": "https://www.bloomberg.com/news/articles/2026-06-16/emerging-stocks-near-record-high-on-tech-gains-lower-oil-prices",
    "published": "Tue, 16 Jun 2026 09:34:27 GMT",
    "source": "Bloomberg",
    "fetched_at": "2026-06-16T11:35:58.325444"
  },
  {
    "id": "14ebe780f40e",
    "title": "AI Stock Rally Is in Boom Phase Not Euphoria, BofA Survey Shows",
    "summary": "The boom in artificial-intelligence stocks looks set to run further, according to a Bank of America Corp. survey, which found the majority of investors believe that the fear of missing out is continuing to drive the trade.",
    "link": "https://www.bloomberg.com/news/articles/2026-06-16/ai-stock-rally-is-in-boom-phase-not-euphoria-bofa-survey-shows",
    "published": "Tue, 16 Jun 2026 09:29:27 GMT",
    "source": "Bloomberg",
    "fetched_at": "2026-06-16T11:35:58.325449"
  },
  {
    "id": "d60273391754",
    "title": "Bonds Extend Rally as Oil Falls to Lowest Since March",
    "summary": "",
    "link": "https://www.bloomberg.com/news/live-blog/2026-06-16/ftse-100-live-pound-gilts-iran-trump-oil-prices-hormuz-g7-ai-stocks-what-s-moving-uk-markets-right-now-markets-today",
    "published": "Tue, 16 Jun 2026 05:45:27 GMT",
    "source": "Bloomberg",
    "fetched_at": "2026-06-16T11:35:58.325454"
  }
]