[
  {
    "id": "eca79d5a3187",
    "title": "Trump Reimposes Iran Blockade, Recommends Graham's Sister, More",
    "title_cn": "特朗普重新实施伊朗封锁，推荐格雷厄姆的妹妹等等",
    "summary": "Source: Bloomberg, 0:00",
    "link": "https://www.bloomberg.com/news/audio/2026-07-13/trump-reimposes-iran-blockade-recommends-graham-s-sister-more",
    "published": "Mon, 13 Jul 2026 15:38:13 GMT",
    "source": "International",
    "fetched_at": "2026-07-13T15:58:07.662428"
  },
  {
    "id": "5f73565a6ee5",
    "title": "Stock Movers: TriCo Bancshares, SK Hynix, Humana (Podcast)",
    "title_cn": "股票推动者：TriCo Bancshares、SK Hynix、Humana（播客）",
    "summary": "Source: Bloomberg, 0:00",
    "link": "https://www.bloomberg.com/news/audio/2026-07-13/stock-movers-trico-bancshares-sk-hynix-humana-podcast",
    "published": "Mon, 13 Jul 2026 15:30:02 GMT",
    "source": "International",
    "fetched_at": "2026-07-13T15:58:08.335112"
  },
  {
    "id": "2fbe00ae7c6c",
    "title": "Bloomberg Talks: Ed Bastian (Podcast)",
    "title_cn": "彭博社谈话：埃德·巴斯蒂安（播客）",
    "summary": "Source: Bloomberg, 8:43",
    "link": "https://www.bloomberg.com/news/audio/2026-07-13/bloomberg-talks-ed-bastian-podcast",
    "published": "Mon, 13 Jul 2026 15:23:16 GMT",
    "source": "International",
    "fetched_at": "2026-07-13T15:58:08.620582"
  },
  {
    "id": "615611af8bdb",
    "title": "Bloomberg Talks: Steve Pagliuca (Podcast)",
    "title_cn": "彭博社谈话：史蒂夫·帕柳卡（播客）",
    "summary": "Source: Bloomberg, 6:11",
    "link": "https://www.bloomberg.com/news/audio/2026-07-13/bloomberg-talks-steve-pagliuca-podcast",
    "published": "Mon, 13 Jul 2026 15:21:12 GMT",
    "source": "International",
    "fetched_at": "2026-07-13T15:58:09.007988"
  },
  {
    "id": "15ed41c9aa93",
    "title": "Stock Movers: SK Hynix, Blackstone, TriCo Bancshares (Podcast)",
    "title_cn": "股票推动者：SK Hynix、Blackstone、TriCo Bancshares（播客）",
    "summary": "Source: Bloomberg, 0:00",
    "link": "https://www.bloomberg.com/news/audio/2026-07-13/stock-movers-sk-hynix-blackstone-trico-bancshares-podcast",
    "published": "Mon, 13 Jul 2026 14:35:19 GMT",
    "source": "International",
    "fetched_at": "2026-07-13T15:58:09.425674"
  },
  {
    "id": "d5583bb6118e",
    "title": "Trump Touts 20% Hormuz Fee, SK Hynix ADRs Tumble, More",
    "title_cn": "特朗普吹捧 20% 霍尔木兹收费、SK 海力士 ADR 暴跌等",
    "summary": "Source: Bloomberg, 0:00",
    "link": "https://www.bloomberg.com/news/audio/2026-07-13/trump-touts-20-hormuz-fee-sk-hynix-adrs-tumble-more",
    "published": "Mon, 13 Jul 2026 14:31:49 GMT",
    "source": "International",
    "fetched_at": "2026-07-13T15:58:09.930996"
  },
  {
    "id": "824428a14628",
    "title": "TransDigm Calls Off Deal for Rival After DOJ Lawsuit Threat",
    "title_cn": "TransDigm 在受到司法部诉讼威胁后取消了与竞争对手的交易",
    "summary": "Aerospace parts maker TransDigm walked away from its $960 million takeover of rival company Stellant Systems after the US Justice Department threatened to sue to block the deal over antitrust concerns.",
    "link": "https://www.bloomberg.com/news/articles/2026-07-13/transdigm-calls-off-deal-for-rival-after-doj-merger-scrutiny",
    "published": "Mon, 13 Jul 2026 12:56:06 GMT",
    "source": "International",
    "fetched_at": "2026-07-13T15:58:10.054512"
  },
  {
    "id": "990741dca026",
    "title": "London IPO Revival Faces Setback as Hopefuls Consider Delays",
    "title_cn": "伦敦IPO复兴面临挫折，希望者考虑推迟",
    "summary": "Several UK companies including Waterstones Booksellers Ltd. and SumUp Payments Ltd. are considering deferring their initial public offerings in London to 2027, according to people familiar with the matter, denting the capital’s hopes for a substantial revival in listings activity this year.",
    "link": "https://www.bloomberg.com/news/articles/2026-07-13/waterstones-sumup-are-said-to-weigh-pushing-london-ipos-to-2027",
    "published": "Mon, 13 Jul 2026 14:22:59 GMT",
    "source": "International",
    "fetched_at": "2026-07-13T15:58:10.194894"
  },
  {
    "id": "e966dc5ceb21",
    "title": "Stock Movers: MGM, SKHY, AGEN (Podcast)",
    "title_cn": "库存推动者：MGM、SKHY、AGEN（播客）",
    "summary": "Source: Bloomberg, 0:00",
    "link": "https://www.bloomberg.com/news/audio/2026-07-13/stock-movers-mgm-skhy-agen-podcast",
    "published": "Mon, 13 Jul 2026 13:43:10 GMT",
    "source": "International",
    "fetched_at": "2026-07-13T15:58:10.311218"
  },
  {
    "id": "febaac332893",
    "title": "Korean Chip Stocks And A Bursting Bubble: Macro Man Podcast",
    "title_cn": "韩国芯片股和泡沫破灭：宏观人播客",
    "summary": "Source: Bloomberg, 5:17",
    "link": "https://www.bloomberg.com/news/audio/2026-07-13/korean-chip-stocks-and-a-bursting-bubble-macro-man-podcast",
    "published": "Mon, 13 Jul 2026 13:41:09 GMT",
    "source": "International",
    "fetched_at": "2026-07-13T15:58:10.414041"
  },
  {
    "id": "8b671eb3a629",
    "title": "Stocks Open Week Lower, Trump: US Will Take Over Hormuz, More",
    "title_cn": "特朗普：美国将接管霍尔木兹海峡，股市本周低开",
    "summary": "Source: Bloomberg, 0:00",
    "link": "https://www.bloomberg.com/news/audio/2026-07-13/stocks-open-week-lower-trump-us-will-take-over-hormuz-more",
    "published": "Mon, 13 Jul 2026 13:38:29 GMT",
    "source": "International",
    "fetched_at": "2026-07-13T15:58:10.827556"
  },
  {
    "id": "24f95f8e9140",
    "title": "Bloomberg Surveillance: Market Jitters (Podcast)",
    "title_cn": "彭博监测：市场不安（播客）",
    "summary": "Source: Bloomberg, 0:00",
    "link": "https://www.bloomberg.com/news/audio/2026-07-13/bloomberg-surveillance-market-jitters-podcast",
    "published": "Mon, 13 Jul 2026 13:29:29 GMT",
    "source": "International",
    "fetched_at": "2026-07-13T15:58:11.089718"
  },
  {
    "id": "2f9987f6490b",
    "title": "Seahawks Become Latest Record Breakers in Sports M&amp;A",
    "title_cn": "海鹰队成为体育并购领域的最新纪录打破者",
    "summary": "Values have been steadily rising in sports, with records set across American football, baseball and basketball.",
    "link": "https://www.bloomberg.com/news/newsletters/2026-07-13/seattle-seahawks-become-latest-record-breakers-in-sports-m-a",
    "published": "Mon, 13 Jul 2026 13:07:36 GMT",
    "source": "International",
    "fetched_at": "2026-07-13T15:58:11.493540"
  },
  {
    "id": "f78857f00acb",
    "title": "EU Agreement on Next Russia Sanctions Package Remains Elusive",
    "title_cn": "欧盟关于下一个俄罗斯制裁方案的协议仍然难以实现",
    "summary": "The bloc had been due to sign off on the 21st sanctions package against Russia",
    "link": "https://www.bloomberg.com/news/newsletters/2026-07-13/eu-discusses-latest-russian-sanctions-package-and-israel-trade",
    "published": "Mon, 13 Jul 2026 13:03:02 GMT",
    "source": "International",
    "fetched_at": "2026-07-13T15:58:12.297488"
  },
  {
    "id": "9c77cafb9cd4",
    "title": "War Sparks a New African Scramble for Energy Security",
    "title_cn": "战争引发非洲新一轮能源安全争夺",
    "summary": "Fears of running out of the fuel that still drives levers of business have returned.",
    "link": "https://www.bloomberg.com/news/newsletters/2026-07-13/next-africa-iran-war-sparks-a-new-scramble-for-energy-security",
    "published": "Mon, 13 Jul 2026 13:00:11 GMT",
    "source": "International",
    "fetched_at": "2026-07-13T15:58:12.424054"
  },
  {
    "id": "e1eb041b0008",
    "title": "Trump Says US Is Taking Over Hormuz, Chip Selloff, More",
    "title_cn": "特朗普称美国正在接管霍尔木兹海峡、芯片抛售等",
    "summary": "Source: Bloomberg, 0:00",
    "link": "https://www.bloomberg.com/news/audio/2026-07-13/trump-says-us-is-taking-over-hormuz-chip-selloff-more",
    "published": "Mon, 13 Jul 2026 12:52:28 GMT",
    "source": "International",
    "fetched_at": "2026-07-13T15:58:12.911452"
  },
  {
    "id": "212e172b0667",
    "title": "Abu Dhabi’s Hedge Fund Push Enters New Phase",
    "title_cn": "阿布扎比的对冲基金推动进入新阶段",
    "summary": "The emirate is deploying its sovereign wealth to become one of the hedge fund industry’s biggest sources of capital.",
    "link": "https://www.bloomberg.com/news/newsletters/2026-07-13/abu-dhabi-s-hedge-fund-push-enters-new-phase-saudi-uae-rift-worries-wall-street",
    "published": "Mon, 13 Jul 2026 12:31:33 GMT",
    "source": "International",
    "fetched_at": "2026-07-13T15:58:13.020582"
  },
  {
    "id": "dd86411f00da",
    "title": "How India Is Unlocking the Value of Its Gold Obsession",
    "title_cn": "印度如何释放其对黄金的痴迷的价值",
    "summary": "Gold loans account for 11% of all outstanding consumer credit.",
    "link": "https://www.bloomberg.com/news/newsletters/2026-07-13/how-india-is-unlocking-the-value-of-its-gold-obsession",
    "published": "Mon, 13 Jul 2026 12:27:36 GMT",
    "source": "International",
    "fetched_at": "2026-07-13T15:58:13.139955"
  },
  {
    "id": "6bd5b59a3dcf",
    "title": "Stellantis CEO Struggles to Win Over Investors for Turnaround Plan",
    "title_cn": "Stellantis 首席执行官努力为扭亏为盈计划赢得投资者",
    "summary": "The Jeep maker’s shares are still hovering near record lows after a series of stumbles.",
    "link": "https://www.bloomberg.com/news/newsletters/2026-07-13/stellantis-ceo-struggles-to-win-over-investors-for-turnaround-plan",
    "published": "Mon, 13 Jul 2026 12:26:04 GMT",
    "source": "International",
    "fetched_at": "2026-07-13T15:58:13.870483"
  },
  {
    "id": "707630fcd3fb",
    "title": "Tech Disruptors: IOWN’s Wright, Wang on Photonics-Based Networks",
    "title_cn": "技术颠覆者：IOWN 的 Wright、Wang 谈基于光子学的网络",
    "summary": "The accelerating shift toward photonics-based networks &mdash; using light to transmit data &mdash; can help unlock the full potential of the AI economy. In this episode of the Tech Disruptors podcast, IOWN Global Forum board members Chris Wright (chief technology officer and senior vice president of global engineering, Red Hat) and Jefferson Wang (chief strategy &amp; innovation officer, cloud, Accenture) talk through how this next-generation technology will replace electrical-based connectivity with optic",
    "link": "https://www.bloomberg.com/news/audio/2026-07-13/tech-disruptors-iown-s-wright-wang-on-photonics-based-networks",
    "published": "Mon, 13 Jul 2026 12:00:00 GMT",
    "source": "International",
    "fetched_at": "2026-07-13T15:58:14.868273"
  },
  {
    "id": "2bd8823ae43c",
    "title": "US and Iran Trade Fresh Strikes, Remembering Lindsey Graham",
    "title_cn": "美国和伊朗进行新一轮打击，纪念林赛·格雷厄姆",
    "summary": "Source: Bloomberg, 0:00",
    "link": "https://www.bloomberg.com/news/audio/2026-07-13/us-and-iran-trade-fresh-strikes-remembering-lindsey-graham",
    "published": "Mon, 13 Jul 2026 11:28:14 GMT",
    "source": "International",
    "fetched_at": "2026-07-13T15:58:15.418584"
  },
  {
    "id": "ea460f5cc322",
    "title": "Saudi Energy Minister’s Influence Grows With Industry Portfolio",
    "title_cn": "沙特能源部长的影响力随着行业组合的增长而增长",
    "summary": "Saudi Arabian Energy Minister Prince Abdulaziz bin Salman was appointed minister of industry and mineral resources in addition to his current post, signaling an expanded role for the royal and closer integration of the two sectors.",
    "link": "https://www.bloomberg.com/news/articles/2026-07-13/saudi-energy-minister-s-influence-grows-with-industry-portfolio",
    "published": "Mon, 13 Jul 2026 11:17:59 GMT",
    "source": "International",
    "fetched_at": "2026-07-13T15:58:15.577792"
  },
  {
    "id": "312093907830",
    "title": "US and Iran Trade Fresh Strikes, Dispute Whether Hormuz Is Open",
    "title_cn": "美国和伊朗进行新的打击，对霍尔木兹是否开放存在争议",
    "summary": "Here’s what you need to know to start your day",
    "link": "https://www.bloomberg.com/news/newsletters/2026-07-13/us-and-iran-trade-fresh-strikes-dispute-whether-hormuz-is-open-mrj4a91x",
    "published": "Mon, 13 Jul 2026 11:06:25 GMT",
    "source": "International",
    "fetched_at": "2026-07-13T15:58:15.718087"
  },
  {
    "id": "bc13fc78c5db",
    "title": "Stock Movers: SKHY, TSM; CNMD (Podcast)",
    "title_cn": "库存搬运商：SKHY、TSM； CNMD（播客）",
    "summary": "Source: Bloomberg, 4:40",
    "link": "https://www.bloomberg.com/news/audio/2026-07-13/stock-movers-skhy-tsm-cnmd-podcast",
    "published": "Mon, 13 Jul 2026 11:01:49 GMT",
    "source": "International",
    "fetched_at": "2026-07-13T15:58:16.624628"
  },
  {
    "id": "34e530afa4a5",
    "title": "Credit Crunch: Xponance’s McElreath on Credit Inefficiencies",
    "title_cn": "信贷紧缩：Xponance 的 McElreath 谈信贷效率低下",
    "summary": "“The portfolio manager’s dilemma is, ‘Do I take risk, or do I not take risk?’” Noel McElreath, senior portfolio manager for US fixed income at Xponance, tells Bloomberg Intelligence’s Noel Hebert. “And then, ‘What is excess return telling me?’” On this episode of Credit Crunch, the pair discuss the importance of disciplined credit selection, exploiting structural inefficiencies and maintaining a long-term perspective. McElreath notes that, though current market conditions are favorable, tight sp",
    "link": "https://www.bloomberg.com/news/audio/2026-07-13/credit-crunch-xponance-s-mcelreath-on-credit-inefficiencies",
    "published": "Mon, 13 Jul 2026 10:30:00 GMT",
    "source": "International",
    "fetched_at": "2026-07-13T15:58:16.755466"
  },
  {
    "id": "0dac7d823fc6",
    "title": "US-Iran Strikes Escalate, Lindsey Graham's Legacy, More",
    "title_cn": "美伊袭击升级、林赛·格雷厄姆的遗产等等",
    "summary": "Source: Bloomberg, 5:36",
    "link": "https://www.bloomberg.com/news/audio/2026-07-13/us-iran-strikes-escalate-lindsey-graham-s-legacy-more",
    "published": "Mon, 13 Jul 2026 10:22:57 GMT",
    "source": "International",
    "fetched_at": "2026-07-13T15:58:16.868169"
  },
  {
    "id": "abd6a8d83828",
    "title": "Bloomberg Daybreak: US-Iran Strikes (Podcast)",
    "title_cn": "彭博黎明：美伊袭击（播客）",
    "summary": "Source: Bloomberg, 15:28",
    "link": "https://www.bloomberg.com/news/audio/2026-07-13/bloomberg-daybreak-us-iran-strikes-podcast",
    "published": "Mon, 13 Jul 2026 09:32:18 GMT",
    "source": "International",
    "fetched_at": "2026-07-13T15:58:16.996125"
  },
  {
    "id": "c336cfc46479",
    "title": "US and Iran Trade Fresh Strikes, Lindsey Graham’s Death, More",
    "title_cn": "美国和伊朗进行新一轮袭击、林赛·格雷厄姆之死等",
    "summary": "Source: Bloomberg, 5:45",
    "link": "https://www.bloomberg.com/news/audio/2026-07-13/us-and-iran-trade-fresh-strikes-lindsey-graham-s-death-more",
    "published": "Mon, 13 Jul 2026 09:24:38 GMT",
    "source": "International",
    "fetched_at": "2026-07-13T15:58:17.121813"
  },
  {
    "id": "3d346f055120",
    "title": "Stock Movers: Akzo Nobel, Anglo American, Pagegroup (Podcast)",
    "title_cn": "股票推动者：阿克苏诺贝尔、英美资源集团、Pagegroup（播客）",
    "summary": "Source: Bloomberg, 4:25",
    "link": "https://www.bloomberg.com/news/audio/2026-07-13/stock-movers-akzo-nobel-anglo-american-pagegroup-podcast",
    "published": "Mon, 13 Jul 2026 09:16:42 GMT",
    "source": "International",
    "fetched_at": "2026-07-13T15:58:17.243566"
  },
  {
    "id": "3ab694b15c91",
    "title": "Korean Stocks Are Most Volatile Since 1998 Asian Financial Crisis",
    "title_cn": "韩国股市自 1998 年亚洲金融危机以来波动最为剧烈",
    "summary": "Get caught up.",
    "link": "https://www.bloomberg.com/news/newsletters/2026-07-13/korean-stocks-are-most-volatile-since-1998-asian-financial-crisis",
    "published": "Mon, 13 Jul 2026 09:16:15 GMT",
    "source": "International",
    "fetched_at": "2026-07-13T15:58:17.344563"
  },
  {
    "id": "402c5b1d9d1c",
    "title": "European Stocks Steady as Energy Offsets Travel, Tech Losses",
    "title_cn": "由于能源抵消了旅行和科技股的损失，欧洲股市保持稳定",
    "summary": "European stocks were muted as declines in tech and travel shares were offset by gains in the energy sector, which was lifted by higher oil prices.",
    "link": "https://www.bloomberg.com/news/articles/2026-07-13/european-stocks-drop-after-us-iran-strikes-oil-lifts-energy",
    "published": "Mon, 13 Jul 2026 07:30:09 GMT",
    "source": "International",
    "fetched_at": "2026-07-13T15:58:17.730959"
  },
  {
    "id": "312a92d3a967",
    "title": "Trump Says US Will Be Reimbursed 20% Rate for Hormuz Traffic",
    "title_cn": "特朗普称美国将获得霍尔木兹海峡交通20%的补偿",
    "summary": "President Donald Trump said the US would reinstate its blockade of Iranian ships transiting the Strait of Hormuz and demanded a 20% reimbursement on all other cargo shipped through the waterway.",
    "link": "https://www.bloomberg.com/news/articles/2026-07-13/trump-says-us-will-be-reimbursed-20-rate-for-hormuz-traffic",
    "published": "Mon, 13 Jul 2026 14:25:52 GMT",
    "source": "International",
    "fetched_at": "2026-07-13T15:58:17.875946"
  },
  {
    "id": "d53ba6dfe175",
    "title": "UBS Sees Goldman, JPMorgan in Focus on Busy Earnings Day",
    "title_cn": "瑞银认为高盛和摩根大通将在繁忙的财报日聚焦",
    "summary": "UBS Group AG analyst Erika Najarian says Goldman Sachs Group Inc. may have the tallest order when it comes to demonstrating earnings prowess this week, while investors may be focused on more on succession at JPMorgan Chase & Co. She previews Wall Street bank earnings on \"Bloomberg Surveillance.\" (Source: Bloomberg)",
    "link": "https://www.bloomberg.com/news/videos/2026-07-13/ubs-sees-goldman-jpmorgan-in-focus-on-busy-earnings-day-video",
    "published": "Mon, 13 Jul 2026 15:41:47 GMT",
    "source": "International",
    "fetched_at": "2026-07-13T15:58:20.406563"
  },
  {
    "id": "073b2459b0be",
    "title": "Oil Rallies as Trump Says US Will Be Paid 20% for Hormuz Flows",
    "title_cn": "特朗普称美国将因霍尔木兹海峡流量支付 20%，油价上涨",
    "summary": "Oil jumped after US President Donald Trump said he would reimpose a blockade on Iranian ships transiting the Strait of Hormuz and demand a payment for all other cargo moving through the waterway, dashing hopes for a near-term recovery in shipping flows.",
    "link": "https://www.bloomberg.com/news/articles/2026-07-12/latest-oil-market-news-and-analysis-for-july-13",
    "published": "Sun, 12 Jul 2026 22:02:12 GMT",
    "source": "International",
    "fetched_at": "2026-07-13T15:58:20.512497"
  },
  {
    "id": "020b91243d38",
    "title": "Top Risks Facing Bank Earnings",
    "title_cn": "银行盈利面临的主要风险",
    "summary": "Big bank earnings kick off with expectations running sky-high. KBW's Chris McGratty joins Open Interest to explain why capital markets remain a major tailwind, why deposit costs and credit quality could become the biggest risks, and why Morgan Stanley stands out as his top large-bank pick despite rich valuations. (Source: Bloomberg)",
    "link": "https://www.bloomberg.com/news/videos/2026-07-13/top-risks-facing-bank-earnings-video",
    "published": "Mon, 13 Jul 2026 15:25:22 GMT",
    "source": "International",
    "fetched_at": "2026-07-13T15:58:20.648403"
  },
  {
    "id": "5bd977628f17",
    "title": "Apollo’s Slok Warns of Dollar’s Vulnerability to an AI Pullback",
    "title_cn": "Apollo 的 Slok 警告美元容易受到人工智能回调的影响",
    "summary": "The dollar’s recent gains are at risk if the selloff in artificial intelligence stocks deepens, according to Apollo Global Management Inc.’s Torsten Slok.",
    "link": "https://www.bloomberg.com/news/articles/2026-07-13/apollo-s-slok-warns-of-dollar-s-vulnerability-to-an-ai-pullback",
    "published": "Mon, 13 Jul 2026 15:21:45 GMT",
    "source": "International",
    "fetched_at": "2026-07-13T15:58:20.766626"
  },
  {
    "id": "dfa9765fb06f",
    "title": "American Aid Worker With Ebola ‘Stable’ in German Hospital",
    "title_cn": "感染埃博拉病毒的美国援助人员在德国医院“病情稳定”",
    "summary": "An American aid worker who tested positive for Ebola is stable and being treated in a specialized isolation unit at Frankfurt University Hospital in Germany, according to a statement from the hospital.",
    "link": "https://www.bloomberg.com/news/articles/2026-07-13/american-aid-worker-with-ebola-stable-in-german-hospital",
    "published": "Mon, 13 Jul 2026 15:18:20 GMT",
    "source": "International",
    "fetched_at": "2026-07-13T15:58:20.872879"
  },
  {
    "id": "57b2bede7def",
    "title": "Wall Street Banks Set to Pull in Almost $39 Billion From Trading",
    "title_cn": "华尔街银行将从交易中吸纳近 390 亿美元",
    "summary": "The biggest US banks &mdash; set to kick off a marathon Tuesday with five of those firms reporting second-quarter earnings &mdash; are reaping the benefits of a volatile past few months that’s spurred more action from clients wanting to trade.\nChris McGratty, Head of US Bank Research at KBW, previews what to expect from bank earnings. (Source: Bloomberg)",
    "link": "https://www.bloomberg.com/news/videos/2026-07-13/wall-street-banks-to-pull-in-almost-39b-from-trading-video",
    "published": "Mon, 13 Jul 2026 15:08:58 GMT",
    "source": "International",
    "fetched_at": "2026-07-13T15:58:21.029730"
  },
  {
    "id": "a9db61d74668",
    "title": "Stocks Fall as Hormuz Standoff Spurs Rally in Oil: Markets Wrap",
    "title_cn": "霍尔木兹僵局刺激石油反弹，股市下跌：市场总结",
    "summary": "A standoff between the US and Iran lifted oil prices, dragging down stocks and bonds after clashes over the Strait of Hormuz raised concerns about a disruption in energy supplies that could fuel inflation.",
    "link": "https://www.bloomberg.com/news/articles/2026-07-12/oil-climbs-us-futures-dip-on-fresh-iran-strikes-markets-wrap",
    "published": "Sun, 12 Jul 2026 22:10:28 GMT",
    "source": "International",
    "fetched_at": "2026-07-13T15:58:21.176250"
  },
  {
    "id": "020595791484",
    "title": "Gold Tumbles as US-Iran Strikes Heighten Fed Rate Hike Bets",
    "title_cn": "美伊冲突加剧美联储加息押注 金价暴跌",
    "summary": "Gold dropped the most in more than two weeks as renewed US-Iran hostilities in the Middle East sent oil prices higher, fueling expectations that the Federal Reserve may have to raise interest rates to contain inflation.",
    "link": "https://www.bloomberg.com/news/articles/2026-07-12/gold-declines-as-renewed-us-iran-strikes-raise-rate-hike-bets",
    "published": "Sun, 12 Jul 2026 23:13:35 GMT",
    "source": "International",
    "fetched_at": "2026-07-13T15:58:21.306756"
  },
  {
    "id": "f247ed020c95",
    "title": "US to Raise Mexico Sugar Imports to 1.15 Million Metric Tons",
    "title_cn": "美国拟将墨西哥食糖进口量增加至 115 万吨",
    "summary": "The US Department of Agriculture estimates it will import as much as 1.15 million metric tons of Mexican sugar in the 2026-2027 period, according to a statement posted on X by Mexican President Claudia Sheinbaum.",
    "link": "https://www.bloomberg.com/news/articles/2026-07-13/us-to-increase-mexico-sugar-imports-to-1-15-million-metric-tons",
    "published": "Mon, 13 Jul 2026 01:25:45 GMT",
    "source": "International",
    "fetched_at": "2026-07-13T15:58:21.469387"
  },
  {
    "id": "9f37eab42b1f",
    "title": "Tech Stocks Slide as Oil Climbs on Hormuz Standoff",
    "title_cn": "霍尔木兹对峙导致石油价格上涨，科技股下跌",
    "summary": "A selloff in tech giants sent stocks lower, with the market also falling as oil jumped after clashes over the Strait of Hormuz raised concerns about a disruption in energy supplies that could fuel inflation.\nStuart Kaiser, Head: US Equity Trading Strategy at Citi gives his outlook on the markets and looks ahead to June CPI out Tuesday. (Source: Bloomberg)",
    "link": "https://www.bloomberg.com/news/videos/2026-07-13/tech-stocks-slide-as-oil-climbs-on-hormuz-standoff-video",
    "published": "Mon, 13 Jul 2026 14:46:57 GMT",
    "source": "International",
    "fetched_at": "2026-07-13T15:58:21.592053"
  },
  {
    "id": "38991700c8b8",
    "title": "Oil Rallies as Conflict Over Hormuz Escalates With Fresh Strikes",
    "title_cn": "霍尔木兹冲突升级，新一轮罢工导致石油价格上涨",
    "summary": "Oil gained after the US carried out another wave of strikes against Iran, with the two sides disputing whether the Strait of Hormuz was open.\nEd Morse, Senior Advisor and Commodity Strategist at Hartree Partners, discusses what's next for energy markets amid uncertainty in the Strait of Hormuz. (Source: Bloomberg)",
    "link": "https://www.bloomberg.com/news/videos/2026-07-13/oil-rallies-as-conflict-over-hormuz-escalates-video",
    "published": "Mon, 13 Jul 2026 14:45:37 GMT",
    "source": "International",
    "fetched_at": "2026-07-13T15:58:21.720860"
  },
  {
    "id": "06edfaac7247",
    "title": "Copper Rises as Traders Weigh Demand After US-Iran Strikes",
    "title_cn": "铜价上涨，交易商在美伊袭击后权衡需求",
    "summary": "Copper edged higher as traders weighed the outlook for demand after renewed hostilities between the US and Iran fueled concerns about global economic growth.",
    "link": "https://www.bloomberg.com/news/articles/2026-07-13/base-metals-decline-as-us-iran-flare-up-clouds-demand-outlook",
    "published": "Mon, 13 Jul 2026 04:31:13 GMT",
    "source": "International",
    "fetched_at": "2026-07-13T15:58:21.842075"
  },
  {
    "id": "4350d18b2b8e",
    "title": "MGM Rises on Takeover Bid; SK Hynix Falls on Memory Pullback | Stock Movers",
    "title_cn": "米高梅收购要约上涨； SK海力士因内存回调而下跌|库存搬运工",
    "summary": "On this episode of Stock Movers:\n\n- MGM Resorts International (MGM) shares are rising on a report regarding a potential takeover bid from Barry Diller.\n- SK Hynix (SKHY) shares are lower and other memory stocks are also falling. It is lower over concerns with the sustainability of artificial-intelligence spending. The drop in South Korean trading is likely to cause a hit to the American depositary receipts as well. The debate between the optimists and pessimists will continue, which should create volatility, according to Hendi Susanto, portfolio manager at Gabelli Funds.\n- Agenus (AGEN) shares are moving higher on news of a deal that it's selling up to $3540 million worth of securities. (Source: Bloomberg)",
    "link": "https://www.bloomberg.com/news/videos/2026-07-13/mgm-up-on-takeover-bid-sk-hynix-down-on-memory-pullback-video",
    "published": "Mon, 13 Jul 2026 14:39:02 GMT",
    "source": "International",
    "fetched_at": "2026-07-13T15:58:21.957693"
  },
  {
    "id": "a15d4f529ead",
    "title": "Treasury Two-Year Yields Rise to Highest Since 2025 as Oil Jumps",
    "title_cn": "随着油价上涨，两年期国债收益率升至 2025 年以来最高",
    "summary": "Short-maturity US Treasury yields climbed to their highest levels since early 2025 as renewed tensions with Iran pushed up oil prices, fanning speculation that the Federal Reserve will need to raise interest rates to combat inflation.",
    "link": "https://www.bloomberg.com/news/articles/2026-07-13/treasury-two-year-yield-rises-to-highest-since-2025-on-oil-gain",
    "published": "Mon, 13 Jul 2026 01:07:16 GMT",
    "source": "International",
    "fetched_at": "2026-07-13T15:58:22.106868"
  },
  {
    "id": "bfd411a22d59",
    "title": "Millennium Taps JPMorgan Veteran to Lead New Push Into Brazil",
    "title_cn": "Millennium 聘请摩根大通资深人士领导进军巴西的新举措",
    "summary": "Billionaire Izzy Englander’s Millennium Management is expanding into Latin America’s biggest economy.",
    "link": "https://www.bloomberg.com/news/articles/2026-07-13/millennium-taps-jpmorgan-veteran-to-lead-new-push-into-brazil",
    "published": "Mon, 13 Jul 2026 14:30:47 GMT",
    "source": "International",
    "fetched_at": "2026-07-13T15:58:22.285062"
  },
  {
    "id": "43819717ed96",
    "title": "Trump Says US Would 'Keep the Strait' And Run It",
    "title_cn": "特朗普称美国将“保留并管理海峡”",
    "summary": "The US and Iran have escalated attacks against each other as President Donald Trump says the US will \"keep the Strait\" and \"probably run it.\" Both countries have been offering conflicting statements about whether the Strait of Hormuz is actually open to shipping. Bloomberg's Tyler Kendall reports.  (Source: Bloomberg)",
    "link": "https://www.bloomberg.com/news/videos/2026-07-13/trump-says-us-would-keep-the-strait-and-run-it-video",
    "published": "Mon, 13 Jul 2026 14:01:42 GMT",
    "source": "International",
    "fetched_at": "2026-07-13T15:58:22.573532"
  },
  {
    "id": "7932103d722c",
    "title": "India Pushes State Banks to Step Up Foreign Currency Deposits",
    "title_cn": "印度敦促国有银行增加外币存款",
    "summary": "India has asked state-owned banks to intensify efforts to garner foreign currency deposits from the 35-million-strong diaspora, as the country seeks to boost its external buffers and shore up the flagging rupee.",
    "link": "https://www.bloomberg.com/news/articles/2026-07-13/india-pushes-state-banks-to-step-up-foreign-currency-deposits",
    "published": "Mon, 13 Jul 2026 13:58:53 GMT",
    "source": "International",
    "fetched_at": "2026-07-13T15:58:22.687167"
  },
  {
    "id": "6b23ea34ba3d",
    "title": "US Stocks Fall as Mideast Tensions Flare Anew, Oil Climbs",
    "title_cn": "中东紧张局势再度加剧，油价上涨，美国股市下跌",
    "summary": "US stocks dropped on Monday as investors assessed tit-for-tat attacks between the US and Iran and conflicting information over the status of the Strait of Hormuz.",
    "link": "https://www.bloomberg.com/news/articles/2026-07-13/us-stock-futures-fall-as-mideast-tensions-flare-anew-oil-climbs",
    "published": "Mon, 13 Jul 2026 12:20:56 GMT",
    "source": "International",
    "fetched_at": "2026-07-13T15:58:22.800509"
  },
  {
    "id": "5a86f939d919",
    "title": "Delta CEO Says Oil Prices Will Stay 'Sticky for Longer'",
    "title_cn": "达美航空首席执行官表示油价将“长期保持粘性”",
    "summary": "Delta Air Lines CEO Ed Bastian says oil prices will stay \"sticky for longer,\" but the carrier will still do \"just fine.\" He says there is still strong demand for premium and international travel. He speaks to Bloomberg's Lisa Abramowicz. (Source: Bloomberg)",
    "link": "https://www.bloomberg.com/news/videos/2026-07-13/delta-ceo-says-oil-prices-will-stay-sticky-for-longer-video",
    "published": "Mon, 13 Jul 2026 13:40:21 GMT",
    "source": "International",
    "fetched_at": "2026-07-13T15:58:22.964112"
  },
  {
    "id": "3c13174d98dd",
    "title": "SK Hynix ADRs Tumble in Second Trading Day After Korea Selloff",
    "title_cn": "韩国抛售后，SK 海力士 ADR 在第二个交易日暴跌",
    "summary": "An AI-fueled stock rout in South Korea spilled over into the US market Monday, as SK Hynix Inc. American depositary shares fell as much as 9.3%, underscoring growing investor concerns that the boom is overextended.",
    "link": "https://www.bloomberg.com/news/articles/2026-07-13/sk-hynix-shares-drop-in-seoul-after-much-hyped-us-trading-debut",
    "published": "Mon, 13 Jul 2026 01:27:43 GMT",
    "source": "International",
    "fetched_at": "2026-07-13T15:58:23.071584"
  },
  {
    "id": "033e9801afe4",
    "title": "South Africa Plans First Strategic Oil Boost Since Apartheid",
    "title_cn": "南非计划自种族隔离以来首次战略石油增产",
    "summary": "South Africa plans to increase its strategic oil reserves for the first time since the apartheid government stockpiled crude, adding to measures across the continent to mitigate supply shocks.",
    "link": "https://www.bloomberg.com/news/articles/2026-07-13/south-africa-plans-first-strategic-oil-boost-since-apartheid-era",
    "published": "Mon, 13 Jul 2026 05:21:25 GMT",
    "source": "International",
    "fetched_at": "2026-07-13T15:58:23.191201"
  },
  {
    "id": "828b0872e242",
    "title": "We Tried Out Dyson's New Portable Fan",
    "title_cn": "我们尝试了戴森的新款便携式风扇",
    "summary": "The newest status symbol on the streets of Manhattan is a high-tech portable fan that’s been hard to get hold of. Samantha Kelly tried one of Dyson's new portable fans out in the New York City heat. \n\n (Source: Bloomberg)",
    "link": "https://www.bloomberg.com/news/videos/2026-07-13/we-tried-out-dyson-s-new-portable-fan",
    "published": "Mon, 13 Jul 2026 13:38:03 GMT",
    "source": "International",
    "fetched_at": "2026-07-13T15:58:23.302828"
  },
  {
    "id": "8a54fdaf6f8f",
    "title": "Apple’s $650 Billion Rally Fueled by Traders Fleeing AI Selloff",
    "title_cn": "交易员逃离人工智能抛售推动苹果股价上涨 6500 亿美元",
    "summary": "Investors are flocking back to Apple Inc. as nervousness about artificial intelligence spending weighs on the stocks of chipmakers and cloud-computing giants.",
    "link": "https://www.bloomberg.com/news/articles/2026-07-13/apple-s-600-billion-rally-fueled-by-traders-fleeing-ai-selloff",
    "published": "Mon, 13 Jul 2026 10:13:17 GMT",
    "source": "International",
    "fetched_at": "2026-07-13T15:58:23.405521"
  },
  {
    "id": "ab8124f9bfff",
    "title": "Renewed Iran Woes Flip Script for Traders Betting War Risks Over",
    "title_cn": "伊朗危机重燃，交易员押注战争风险翻转脚本",
    "summary": "A day after making an investment call tied to subsiding Middle East tensions, BCA Research’s Marko Papic had to scrap his recommendation at a loss. Donald Trump had said the war in Iran was back on.",
    "link": "https://www.bloomberg.com/news/articles/2026-07-13/renewed-iran-woes-flip-script-for-traders-betting-war-risks-over",
    "published": "Mon, 13 Jul 2026 11:11:17 GMT",
    "source": "International",
    "fetched_at": "2026-07-13T15:58:23.522418"
  },
  {
    "id": "92b0efc65110",
    "title": "Delta Will Do Just Fine With High Fuel Prices, CEO Says",
    "title_cn": "首席执行官表示达美航空将在高燃油价格下表现良好",
    "summary": "Delta Air Lines Chief Executive Officer Ed Bastian says higher fuel prices are not deterring travel. He says the carrier is actually seeing strong demand for premium, corporate and international travel. He also talks about how some customers are choosing a better seat on the plane over perks they could get in first class. He speaks to Bloomberg's Lisa Abramowicz at Delta headquarters in Hapeville, Georgia on \"Bloomberg Surveillance.\" (Source: Bloomberg)",
    "link": "https://www.bloomberg.com/news/videos/2026-07-13/delta-will-do-just-fine-with-high-fuel-prices-ceo-says-video",
    "published": "Mon, 13 Jul 2026 13:26:52 GMT",
    "source": "International",
    "fetched_at": "2026-07-13T15:58:23.635933"
  },
  {
    "id": "8cd7d087b3c0",
    "title": "Cocoa’s Uneven Demand Recovery Runs Into Fresh Price Volatility",
    "title_cn": "可可需求复苏不均衡引发新的价格波动",
    "summary": "Cocoa demand is expected to remain uneven across the world, suggesting the recovery remains fragile as renewed supply concerns push bean prices higher and threaten to keep chocolate pricier for longer.",
    "link": "https://www.bloomberg.com/news/articles/2026-07-13/cocoa-s-uneven-demand-recovery-runs-into-fresh-price-volatility",
    "published": "Mon, 13 Jul 2026 13:02:34 GMT",
    "source": "International",
    "fetched_at": "2026-07-13T15:58:23.742510"
  },
  {
    "id": "9d828ac1b7d7",
    "title": "US and Iran Trade Strikes, Dispute Whether Hormuz Is Open",
    "title_cn": "美国和伊朗贸易打击，霍尔木兹海峡是否开放存在争议",
    "summary": "The US and Iran exchanged fresh strikes overnight into Monday, prolonging a spate of tit-for-tat attacks at a time when the two nations offer conflicting statements over whether the Strait of Hormuz is open to shipping.",
    "link": "https://www.bloomberg.com/news/articles/2026-07-13/us-and-iran-trade-fresh-strikes-dispute-whether-hormuz-is-open",
    "published": "Mon, 13 Jul 2026 05:31:00 GMT",
    "source": "International",
    "fetched_at": "2026-07-13T15:58:24.027264"
  },
  {
    "id": "cfacc88e4796",
    "title": "FCC Cutting Satellite Approval Lag In Half, Chairman Says",
    "title_cn": "主席表示，FCC 将卫星审批滞后时间缩短了一半",
    "summary": "The Federal Communications Commission has reduced by half the backlog of satellite application approvals as it broadly seeks to stimulate the space and communications economy, Chairman Brendan Carr said in an interview on Bloomberg TV.",
    "link": "https://www.bloomberg.com/news/articles/2026-07-13/fcc-cutting-satellite-approval-lag-in-half-chairman-says",
    "published": "Mon, 13 Jul 2026 15:40:15 GMT",
    "source": "International",
    "fetched_at": "2026-07-13T15:58:24.787423"
  },
  {
    "id": "1fb0f467dc89",
    "title": "Lazard's Bilicic Sees 'Tremendous' Demand for AI Data Center Power",
    "title_cn": "Lazard 的 Bilicic 看到人工智能数据中心电力的“巨大”需求",
    "summary": "George Bilicic, Lazard's global head of power, energy and infrastructure, says we're a long way from solving the issue of energy demand for AI data center power and expects upward pressure on gas prices. He speaks on \"Bloomberg Open Interest.\" (Source: Bloomberg)",
    "link": "https://www.bloomberg.com/news/videos/2026-07-13/lazard-s-bilicic-sees-tremendous-demand-for-ai-power-video",
    "published": "Mon, 13 Jul 2026 15:27:28 GMT",
    "source": "International",
    "fetched_at": "2026-07-13T15:58:24.935014"
  },
  {
    "id": "0bd1712ce172",
    "title": "Sunrun Offers Solar Users Hundreds Per Month in Compute Program",
    "title_cn": "Sunrun 为太阳能用户提供每月数百美元的计算计划",
    "summary": "Sunrun Inc. is piloting a program aimed at enabling customers to earn hundreds of dollars per month that would use electricity from rooftop solar installations to power distributed computing, according to Chief Executive Officer Mary Powell.",
    "link": "https://www.bloomberg.com/news/articles/2026-07-13/sunrun-offers-solar-users-hundreds-per-month-in-compute-program",
    "published": "Mon, 13 Jul 2026 15:21:25 GMT",
    "source": "International",
    "fetched_at": "2026-07-13T15:58:25.061591"
  },
  {
    "id": "dc69d84b6a02",
    "title": "Sunrun's Experiment to Turn Homes Into AI Hubs",
    "title_cn": "Sunrun 将家庭变成人工智能中心的实验",
    "summary": "Sunrun CEO Mary Powell joins Open Interest to explain how the company plans to transform homes with solar and batteries into AI computing hubs. She says homeowners could earn hundreds of dollars a month by hosting AI compute nodes while helping meet soaring demand for AI infrastructure. (Source: Bloomberg)",
    "link": "https://www.bloomberg.com/news/videos/2026-07-13/sunrun-s-experiment-to-turn-homes-into-ai-hubs-video",
    "published": "Mon, 13 Jul 2026 15:20:12 GMT",
    "source": "International",
    "fetched_at": "2026-07-13T15:58:25.920603"
  },
  {
    "id": "d03edbe357a2",
    "title": "General Fusion Soars After Nasdaq Debut",
    "title_cn": "General Fusion 纳斯达克上市后股价飙升",
    "summary": "General Fusion CEO Greg Twinney joins Open Interest after the company's Nasdaq debut, explaining why going public accelerates its fusion roadmap, how fusion could power AI data centers, and why he believes the company's mechanical approach can outperform rival technologies in the global race for commercial fusion energy. (Source: Bloomberg)",
    "link": "https://www.bloomberg.com/news/videos/2026-07-13/general-fusion-soars-after-nasdaq-debut-video",
    "published": "Mon, 13 Jul 2026 15:14:32 GMT",
    "source": "International",
    "fetched_at": "2026-07-13T15:58:26.279907"
  },
  {
    "id": "604752fccfb2",
    "title": "US Gas-Power Costs at 17-Year High and Climbing, Lazard Says",
    "title_cn": "Lazard 称美国天然气发电成本创 17 年来新高且仍在攀升",
    "summary": "The cost of power from natural gas-fired plants in the US hit the highest level in at least 17 years, and is poised to climb even higher as demand surges from new data centers.",
    "link": "https://www.bloomberg.com/news/articles/2026-07-13/us-cost-for-gas-power-at-17-year-high-and-climbing-lazard-says",
    "published": "Mon, 13 Jul 2026 11:00:00 GMT",
    "source": "International",
    "fetched_at": "2026-07-13T15:58:26.398359"
  },
  {
    "id": "f1b2d6c3b05b",
    "title": "AI Chip Giants TSMC and SK Hynix Pull in Different Directions",
    "title_cn": "AI芯片巨头台积电和SK海力士分道扬镳",
    "summary": "TSMC soared while SK Hynix tumbled &mdash; why are are the two essential AI chip firms pulling in different directions?\n\nTom Mackenzie explains. (Source: Bloomberg)",
    "link": "https://www.bloomberg.com/news/videos/2026-07-13/tsmc-and-sk-hynix-pull-in-different-directions-video",
    "published": "Mon, 13 Jul 2026 15:01:32 GMT",
    "source": "International",
    "fetched_at": "2026-07-13T15:58:32.402417"
  },
  {
    "id": "145ea7c3bdce",
    "title": "Intel Invests €5 Billion to Expand Irish Hub in AI Chip Race",
    "title_cn": "英特尔投资 50 亿欧元扩建爱尔兰人工智能芯片竞赛中心",
    "summary": "Intel Corp. is spending €5 billion ($5.7 billion) to expand its plant in Ireland, as the chipmaker attempts to regain its manufacturing dominance for the AI boom.",
    "link": "https://www.bloomberg.com/news/articles/2026-07-13/intel-invests-5-billion-in-irish-hub-to-keep-up-in-ai-chip-race",
    "published": "Mon, 13 Jul 2026 12:02:40 GMT",
    "source": "International",
    "fetched_at": "2026-07-13T15:58:32.618407"
  },
  {
    "id": "2692c5ed7b97",
    "title": "SK Hynix Selloff Is Not a Huge Problem, Kunst Says",
    "title_cn": "Kunst表示，SK海力士抛售并不是一个大问题",
    "summary": "Sarah Kunst, founder and general of Cleo Capital, says the selloff in SK Hynix shares and South Korean stocks is not a problem. Kunst points out that SK Hynix has gained more than 500% over the past year. She speaks on \"Bloomberg Surveillance.\" (Source: Bloomberg)",
    "link": "https://www.bloomberg.com/news/videos/2026-07-13/sk-hynix-selloff-is-not-a-huge-problem-kunst-says-video",
    "published": "Mon, 13 Jul 2026 12:33:06 GMT",
    "source": "International",
    "fetched_at": "2026-07-13T15:58:32.876802"
  },
  {
    "id": "7f377148ce52",
    "title": "Apple’s Lawsuit Threatens to Disrupt OpenAI’s Bid to Rival the iPhone",
    "title_cn": "苹果的诉讼可能会扰乱 OpenAI 与 iPhone 竞争的努力",
    "summary": "Apple Inc.’s lawsuit accusing OpenAI of systematically stealing its intellectual property threatens to disrupt the AI company’s device ambitions long before the case is resolved.",
    "link": "https://www.bloomberg.com/news/articles/2026-07-13/how-apple-s-lawsuit-threatens-to-disrupt-openai-s-bid-to-rival-the-iphone",
    "published": "Mon, 13 Jul 2026 12:32:47 GMT",
    "source": "International",
    "fetched_at": "2026-07-13T15:58:33.705443"
  },
  {
    "id": "12d275e8e97b",
    "title": "ChatGPT’s Upgraded Voice Mode Captures the Imperfections of Real Conversations",
    "title_cn": "ChatGPT 升级语音模式捕捉真实对话的不完美之处",
    "summary": "The OpenAI chatbot now speaks and converses a lot more like a real person",
    "link": "https://www.bloomberg.com/news/newsletters/2026-07-13/chatgpt-s-voice-mode-can-handle-the-um-and-oh-of-real-conversations",
    "published": "Mon, 13 Jul 2026 11:02:01 GMT",
    "source": "International",
    "fetched_at": "2026-07-13T15:58:33.820849"
  },
  {
    "id": "15411bedf28e",
    "title": "Washington Is Looking to Keep China From Training Its AI on US Models",
    "title_cn": "华盛顿希望阻止中国在美国模型上训练人工智能",
    "summary": "<p>Anthropic and OpenAI’s warnings about “adversarial distillation”&nbsp;are reinvigorating one of the oldest debates in Silicon Valley.</p>",
    "link": "https://www.bloomberg.com/news/articles/2026-07-13/anthropic-openai-warnings-prompt-distillation-debate-in-dc",
    "published": "Mon, 13 Jul 2026 11:00:21 GMT",
    "source": "International",
    "fetched_at": "2026-07-13T15:58:33.939566"
  },
  {
    "id": "f825b6c41b01",
    "title": "Researchers Raise Concerns That AI May Atrophy Human Skills",
    "title_cn": "研究人员担心人工智能可能会削弱人类技能",
    "summary": "Will we end up with a generation of experts in high-stakes professions who never build true expertise?",
    "link": "https://www.bloomberg.com/news/newsletters/2026-07-13/ai-risks-never-skilling-new-research-on-loss-of-critical-thinking-skills",
    "published": "Mon, 13 Jul 2026 10:30:01 GMT",
    "source": "International",
    "fetched_at": "2026-07-13T15:58:34.065112"
  },
  {
    "id": "e025b3ab4c1e",
    "title": "Germany’s Smag Sinks in Debut as Defense Stock Appetite Ebbs",
    "title_cn": "由于国防股需求下降，德国 Smag 首次亮相就下跌",
    "summary": "Smag Mobile Antenna Masts AG shares tumbled as much as 33% below the initial public offering price in their German trading debut, marking the latest sign of waning demand for defense stocks in Europe.",
    "link": "https://www.bloomberg.com/news/articles/2026-07-13/antenna-maker-smag-sinks-in-debut-as-defense-stock-appetite-ebbs",
    "published": "Mon, 13 Jul 2026 08:29:29 GMT",
    "source": "International",
    "fetched_at": "2026-07-13T15:58:34.185015"
  },
  {
    "id": "1ef28c540173",
    "title": "Who’s Scamming the Scammers?",
    "title_cn": "谁在欺骗骗子？",
    "summary": "<p>Scambaiting is one way the fed-up masses are dealing with a flood of fraud.</p>",
    "link": "https://www.bloomberg.com/news/articles/2026-07-13/how-scambaiters-fight-online-fraud-scam-texts-and-organized-crime",
    "published": "Mon, 13 Jul 2026 10:00:22 GMT",
    "source": "International",
    "fetched_at": "2026-07-13T15:58:34.323342"
  },
  {
    "id": "04bc1907fc14",
    "title": "Dyson’s New $100 Portable Fan Is Beating the Heat &mdash; and Sales Expectations",
    "title_cn": "戴森 100 美元的新款便携式风扇正在消暑——和销售预期",
    "summary": "The newest status symbol on the streets of Manhattan is a high-tech portable fan that’s been hard to get hold of.",
    "link": "https://www.bloomberg.com/news/articles/2026-07-13/review-dyson-hushjet-mini-cool-fan-is-in-high-demand-this-summer",
    "published": "Mon, 13 Jul 2026 09:30:20 GMT",
    "source": "International",
    "fetched_at": "2026-07-13T15:58:35.580462"
  },
  {
    "id": "2dec3cc5cb71",
    "title": "Meta’s Louisiana Data Center to Surpass $250 Billion Price Tag",
    "title_cn": "Meta 路易斯安那州数据中心的造价将超过 2500 亿美元",
    "summary": "Meta Platforms Inc. has committed to spending an additional $40 billion on its sprawling data center campus in Louisiana, pushing its total expected investment beyond $250 billion for the site as it continues to grow its artificial intelligence computing footprint.",
    "link": "https://www.bloomberg.com/news/articles/2026-07-13/meta-s-louisiana-data-center-to-surpass-250-billion-price-tag",
    "published": "Mon, 13 Jul 2026 09:30:00 GMT",
    "source": "International",
    "fetched_at": "2026-07-13T15:58:35.713259"
  },
  {
    "id": "aa9ed30d8171",
    "title": "EU to Present Plan to Restrict Children’s Access to Social Media",
    "title_cn": "欧盟将提出限制儿童使用社交媒体的计划",
    "summary": "The European Union will propose a law to restrict children’s access to social media, according to the bloc’s top official, as part of a growing global consensus about the harm it causes.",
    "link": "https://www.bloomberg.com/news/articles/2026-07-13/eu-to-present-plan-to-restrict-children-s-access-to-social-media",
    "published": "Mon, 13 Jul 2026 08:44:59 GMT",
    "source": "International",
    "fetched_at": "2026-07-13T15:58:35.840273"
  },
  {
    "id": "50ab85be1aca",
    "title": "Raxio to Enter Tanzania With $380 Million Funding Push",
    "title_cn": "Raxio 斥资 3.8 亿美元进军坦桑尼亚",
    "summary": "Africa-focused data-center firm Raxio Group plans to enter Tanzania as it increases its funding pool to $380 million, Chief Executive Officer Robert Skjødt said.",
    "link": "https://www.bloomberg.com/news/articles/2026-07-13/africa-s-raxio-to-enter-tanzania-with-380-million-funding-push",
    "published": "Mon, 13 Jul 2026 07:23:15 GMT",
    "source": "International",
    "fetched_at": "2026-07-13T15:58:35.975885"
  },
  {
    "id": "a6260df4e77e",
    "title": "TSMC’s Sales Soar 36% in Latest Sign of AI Spending Momentum",
    "title_cn": "人工智能支出势头最新迹象，台积电销售额飙升 36%",
    "summary": "Taiwan Semiconductor Manufacturing Co. reported a 36% jump in quarterly sales, meeting elevated expectations while signaling global demand for AI computing remains intact.",
    "link": "https://www.bloomberg.com/news/articles/2026-07-13/tsmc-sales-surge-36-in-fresh-sign-of-ai-spending-momentum",
    "published": "Mon, 13 Jul 2026 05:40:42 GMT",
    "source": "International",
    "fetched_at": "2026-07-13T15:58:36.078360"
  },
  {
    "id": "b9597615fe8b",
    "title": "Xi to Debut at China’s Flagship AI Summit as US Rivalry Heats Up",
    "title_cn": "习近平将在中国人工智能旗舰峰会上首次亮相，美国竞争加剧",
    "summary": "Chinese President Xi Jinping will make his first appearance at the country’s flagship AI conference, signaling the growing importance Beijing attaches to the technology as its rivalry with the US intensifies.",
    "link": "https://www.bloomberg.com/news/articles/2026-07-13/xi-to-debut-at-china-s-flagship-ai-summit-as-us-rivalry-heats-up",
    "published": "Mon, 13 Jul 2026 08:24:26 GMT",
    "source": "International",
    "fetched_at": "2026-07-13T15:58:36.203240"
  },
  {
    "id": "05dd87afc3b9",
    "title": "Saudi Arabia Becomes Top Buyer in Taiwan’s Young Drone Industry",
    "title_cn": "沙特阿拉伯成为台湾年轻无人机产业的最大买家",
    "summary": "Saudi Arabia bought a record $47.2 million of drones from Taiwan last month &mdash; a sign the island’s nascent UAV industry is becoming more attractive to buyers.",
    "link": "https://www.bloomberg.com/news/articles/2026-07-13/saudi-arabia-becomes-top-buyer-in-taiwan-s-young-drone-industry",
    "published": "Mon, 13 Jul 2026 08:18:37 GMT",
    "source": "International",
    "fetched_at": "2026-07-13T15:58:36.337234"
  },
  {
    "id": "706f5e8e8b82",
    "title": "Why AI Might Actually Create More Work for Lawyers",
    "title_cn": "为什么人工智能实际上可能为律师创造更多工作",
    "summary": "It seems obvious that among the many industries that AI might disrupt, the legal profession might face some of the most adverse outcomes. When clerical, research-based tasks like searching through databases and reading contracts are automated, what is left for lawyers to do and how might they justify all those billable hours? In this episode we speak with Gary Wingens, chair and partner at the law firm Lowenstein Sandler. He talks about how his firm is using AI and why he thinks the technology could end up increasing legal work for lawyers as costs come down, creating a sort of “Jevon's paradox” for lawsuits, deals and litigation. We also talk about the billable hours model and training junior talent. (Source: Bloomberg)",
    "link": "https://www.bloomberg.com/news/videos/2026-07-13/why-ai-might-actually-create-more-work-for-lawyers-video",
    "published": "Mon, 13 Jul 2026 08:14:32 GMT",
    "source": "International",
    "fetched_at": "2026-07-13T15:58:36.444660"
  },
  {
    "id": "613a302c2923",
    "title": "Morgan Stanley’s Wilson Sees Profit Boost for Stocks Beyond Tech",
    "title_cn": "摩根士丹利的威尔逊认为科技股以外的股票利润将得到提振",
    "summary": "US stocks beyond the technology giants are poised to report strong earnings this season, broadening the equity rally, according to Morgan Stanley strategists.",
    "link": "https://www.bloomberg.com/news/articles/2026-07-13/morgan-stanley-s-wilson-sees-profit-boost-for-stocks-beyond-tech",
    "published": "Mon, 13 Jul 2026 07:25:40 GMT",
    "source": "International",
    "fetched_at": "2026-07-13T15:58:36.801050"
  },
  {
    "id": "d0d1f70739b2",
    "title": "South Korea to Tap Record AI Tax Windfall to Fund Future Growth",
    "title_cn": "韩国将利用创纪录的人工智能税收暴利为未来增长提供资金",
    "summary": "South Korea expects to reap a record tax windfall from the artificial intelligence-driven semiconductor boom, giving President Lee Jae Myung’s government fresh fiscal firepower to fund an ambitious investment agenda.",
    "link": "https://www.bloomberg.com/news/articles/2026-07-13/south-korea-to-tap-record-ai-tax-windfall-to-fund-future-growth",
    "published": "Mon, 13 Jul 2026 07:07:33 GMT",
    "source": "International",
    "fetched_at": "2026-07-13T15:58:36.908255"
  },
  {
    "id": "9c5faf6796dd",
    "title": "SK Hynix Shares Slump in South Korea After US Listing",
    "title_cn": "SK海力士在美国上市后韩国股价暴跌",
    "summary": "SK Hynix shares declined in Seoul on Monday after the memory chipmaker’s highly-anticipated US trading debut. The company’s $26.5 billion US offering was closely watched as a test of demand for overseas offerings as well as for the longevity of the artificial intelligence rally. Bloomberg's Neil Campling reports. (Source: Bloomberg)",
    "link": "https://www.bloomberg.com/news/videos/2026-07-13/sk-hynix-shares-slump-in-south-korea-after-us-listing-video",
    "published": "Mon, 13 Jul 2026 05:45:46 GMT",
    "source": "International",
    "fetched_at": "2026-07-13T15:58:37.046594"
  },
  {
    "id": "b643f8a811a2",
    "title": "MiniMax Shares Slump After JPMorgan Cuts Target Price Further",
    "title_cn": "摩根大通进一步下调目标价后 MiniMax 股价暴跌",
    "summary": "MiniMax Group Inc.’s shares plunged, after JPMorgan Chase &amp; Co. slashed the Chinese AI model maker’s price target for the second time in less than a week on value dilution concerns caused by fresh fundraising.",
    "link": "https://www.bloomberg.com/news/articles/2026-07-13/minimax-shares-slump-after-jpmorgan-cuts-target-price-further",
    "published": "Mon, 13 Jul 2026 03:23:30 GMT",
    "source": "International",
    "fetched_at": "2026-07-13T15:58:37.170428"
  },
  {
    "id": "b5a5339febeb",
    "title": "How Once-Struggling SK Hynix Became a Trillion-Dollar Company",
    "title_cn": "曾经陷入困境的 SK 海力士如何成为价值万亿美元的公司",
    "summary": "SK Hynix Inc. is hardly a household name. But the maker of memory chips, which two decades ago was struggling to survive, is now South Korea’s second-most valuable listed company, just behind Samsung Electronics Co.",
    "link": "https://www.bloomberg.com/news/articles/2026-07-10/sk-hynix-what-to-know-about-us-listing-how-it-became-an-ai-powerhouse",
    "published": "Fri, 10 Jul 2026 09:18:09 GMT",
    "source": "International",
    "fetched_at": "2026-07-13T15:58:37.295342"
  },
  {
    "id": "73bfcfe2a33a",
    "title": "アップルのMacチップ戦略転換、自動運転車の「失敗」がAI基盤築く－Power On",
    "title_cn": "苹果Mac芯片战略转变，自动驾驶汽车“失败”为AI奠定基础 - Power On",
    "summary": "中止した自動運転車開発の技術遺産。現在のAI競争力を支える意外な理由とは。",
    "link": "https://www.bloomberg.com/jp/news/newsletters/2026-07-13/TI3F02VTTCZK00",
    "published": "Mon, 13 Jul 2026 03:00:02 GMT",
    "source": "International",
    "fetched_at": "2026-07-13T15:58:37.426091"
  },
  {
    "id": "406631a82c90",
    "title": "UK Counter-Terror Police Lead Probe Into Murder of Ann Widdecombe",
    "title_cn": "英国反恐警察牵头调查安·维德科姆谋杀案",
    "summary": "UK counter-terrorism police said they have taken over the investigation into the murder of Reform politician Ann Widdecombe after new evidence emerged about her death last week.",
    "link": "https://www.bloomberg.com/news/articles/2026-07-13/uk-counter-terror-police-lead-probe-into-murder-of-ex-minister",
    "published": "Mon, 13 Jul 2026 12:52:26 GMT",
    "source": "International",
    "fetched_at": "2026-07-13T15:58:37.797287"
  },
  {
    "id": "967a2ac5a742",
    "title": "Trump Recommends Graham’s Sister Serve Out His Senate Term",
    "title_cn": "特朗普建议格雷厄姆的妹妹完成参议员任期",
    "summary": "President Donald Trump said the late Senator Lindsey Graham’s sister, Darline Graham Nordone, should serve out his term for the South Carolina seat.",
    "link": "https://www.bloomberg.com/news/articles/2026-07-13/trump-recommends-graham-s-sister-to-serve-out-his-senate-term",
    "published": "Mon, 13 Jul 2026 14:58:23 GMT",
    "source": "International",
    "fetched_at": "2026-07-13T15:58:37.944840"
  },
  {
    "id": "57e831885632",
    "title": "US Expands Cuba Sanctions With Targeting of Tourism Industry",
    "title_cn": "美国扩大对古巴制裁，针对旅游业",
    "summary": "The US added Cuba’s Ministry of Tourism to its expanding sanctions list, striking once-again at one of the main economic drivers of the communist-run Caribbean island.",
    "link": "https://www.bloomberg.com/news/articles/2026-07-13/us-expands-cuba-sanctions-with-targeting-of-tourism-industry",
    "published": "Mon, 13 Jul 2026 15:30:28 GMT",
    "source": "International",
    "fetched_at": "2026-07-13T15:58:38.190910"
  },
  {
    "id": "d619e3e87f1d",
    "title": "European Powers Join Forces to Build Anti-Ballistic Systems",
    "title_cn": "欧洲强国联手建立反弹道系统",
    "summary": "A coalition of European nations agreed to share research and industrial experience to build an anti-ballistic missile defense, moving away from its reliance on the US as Ukraine struggles against Russia’s onslaught.",
    "link": "https://www.bloomberg.com/news/articles/2026-07-13/european-powers-join-forces-to-build-anti-ballistic-systems",
    "published": "Mon, 13 Jul 2026 15:24:24 GMT",
    "source": "International",
    "fetched_at": "2026-07-13T15:58:38.332242"
  },
  {
    "id": "3b18dc5d4e46",
    "title": "ICE Involved in Fatal Maine Shooting, State Lawmaker Says",
    "title_cn": "州议员称 ICE 参与了缅因州致命枪击事件",
    "summary": "A person was killed in a shooting involving US Immigration and Customs Enforcement in Maine on Monday morning, the speaker of the state’s House of Representatives said in a social media post.",
    "link": "https://www.bloomberg.com/news/articles/2026-07-13/ice-involved-in-fatal-maine-shooting-state-house-speaker-says",
    "published": "Mon, 13 Jul 2026 14:03:05 GMT",
    "source": "International",
    "fetched_at": "2026-07-13T15:58:38.459716"
  },
  {
    "id": "6c486a62b712",
    "title": "Zurich Ranks Top in Disposable Income Poll Despite $7 Coffees",
    "title_cn": "尽管咖啡价格为 7 美元，苏黎世在可支配收入调查中仍名列前茅",
    "summary": "Zurich and Geneva may be the most expensive places in the world to buy your meat and veg but it’ll still pay off as the two Swiss cities top a new survey of the highest disposable incomes in the world.",
    "link": "https://www.bloomberg.com/news/articles/2026-07-13/zurich-ranks-top-in-disposable-income-poll-despite-7-coffees",
    "published": "Mon, 13 Jul 2026 15:22:11 GMT",
    "source": "International",
    "fetched_at": "2026-07-13T15:58:38.583199"
  },
  {
    "id": "5660cd9d3ef6",
    "title": "Regulators Unveil Guidance Targeting Bank Services to Immigrants",
    "title_cn": "监管机构公布针对移民的银行服务指南",
    "summary": "Top US bank agencies unveiled guidance Monday that calls on lenders to manage the way they engage immigrant clients who may present “elevated” risks.",
    "link": "https://www.bloomberg.com/news/articles/2026-07-13/regulators-unveil-guidance-targeting-bank-services-to-immigrants",
    "published": "Mon, 13 Jul 2026 15:12:28 GMT",
    "source": "International",
    "fetched_at": "2026-07-13T15:58:38.734717"
  },
  {
    "id": "729a6966240c",
    "title": "Crimea Loses Fuel, Water and Power, But Not Russian Tourists",
    "title_cn": "克里米亚失去了燃料、水和电力，但俄罗斯游客却没有",
    "summary": "Russian tourists are continuing to take their summer holidays in Crimea despite persistent Ukrainian drone attacks, a state of emergency, fuel shortages and power outages on the annexed Black Sea peninsula.",
    "link": "https://www.bloomberg.com/news/articles/2026-07-13/crimea-loses-fuel-water-and-power-but-not-russian-tourists",
    "published": "Mon, 13 Jul 2026 13:47:34 GMT",
    "source": "International",
    "fetched_at": "2026-07-13T15:58:38.859056"
  },
  {
    "id": "0b18af3406ea",
    "title": "Putin Puts Akzo Nobel’s Local Assets Under Temporary Control",
    "title_cn": "普京将阿克苏诺贝尔的当地资产置于临时控制之下",
    "summary": "Russian President Vladimir Putin ordered stakes in three Russian companies owned by Dutch paints and coatings maker Akzo Nobel NV transferred to temporary administration.",
    "link": "https://www.bloomberg.com/news/articles/2026-07-13/putin-puts-akzo-nobel-s-russian-assets-under-temporary-control",
    "published": "Mon, 13 Jul 2026 12:46:41 GMT",
    "source": "International",
    "fetched_at": "2026-07-13T15:58:38.960298"
  },
  {
    "id": "3c53d289f808",
    "title": "Pentagon Spending on Mexican Border Operations Tops $2.6 Billion",
    "title_cn": "五角大楼在墨西哥边境行动上的支出突破 26 亿美元",
    "summary": "The Pentagon has spent at least $2.64 billion on operations at the southwest border with Mexico, according to Congress’s audit agency in the most comprehensive cost accounting yet of the military’s expanded role in immigration enforcement.",
    "link": "https://www.bloomberg.com/news/articles/2026-07-13/pentagon-spent-at-least-2-6-billion-on-border-ops-audit-finds",
    "published": "Mon, 13 Jul 2026 14:02:06 GMT",
    "source": "International",
    "fetched_at": "2026-07-13T15:58:39.104631"
  },
  {
    "id": "bdf5eb5052f9",
    "title": "Switzerland and UK Agree Trade Deal to Deepen Post-Brexit Ties",
    "title_cn": "瑞士和英国达成贸易协议以深化脱欧后关系",
    "summary": "Switzerland and the UK concluded talks on an updated free-trade agreement, bringing Western Europe’s two major non-European Union economies closer together with a pact focused on services.",
    "link": "https://www.bloomberg.com/news/articles/2026-07-13/switzerland-and-uk-agree-trade-deal-to-deepen-post-brexit-ties",
    "published": "Mon, 13 Jul 2026 14:00:00 GMT",
    "source": "International",
    "fetched_at": "2026-07-13T15:58:39.262642"
  },
  {
    "id": "e36d5fe7ce39",
    "title": "Merz Urges Currency Dialogue with China as Trade Worries Rise",
    "title_cn": "随着贸易担忧加剧，默茨敦促与中国进行货币对话",
    "summary": "German Chancellor Friedrich Merz reinforced a call for dialogue with China to address concerns that the world’s second-largest economy is shoring up an unfair trade advantage by keeping its currency artificially low.",
    "link": "https://www.bloomberg.com/news/articles/2026-07-13/merz-urges-currency-dialogue-with-china-as-trade-worries-rise",
    "published": "Mon, 13 Jul 2026 13:26:49 GMT",
    "source": "International",
    "fetched_at": "2026-07-13T15:58:39.374549"
  },
  {
    "id": "c5a96e2ad033",
    "title": "Brazil Draft Rule Opens Uranium Mining to Private Partners",
    "title_cn": "巴西规则草案向私人合作伙伴开放铀矿开采",
    "summary": "Brazil plans to open its uranium mining sector to private investment by allowing partnerships with companies, provided the state-owned nuclear company retains at least a 20% stake in each venture, according to a draft regulation seen by Bloomberg.",
    "link": "https://www.bloomberg.com/news/articles/2026-07-13/brazil-draft-rule-opens-uranium-mining-to-private-partners",
    "published": "Mon, 13 Jul 2026 13:07:54 GMT",
    "source": "International",
    "fetched_at": "2026-07-13T15:58:39.502879"
  },
  {
    "id": "5895b831e762",
    "title": "EU to Sanction Sudan’s Gold Trade as Civil War Rages",
    "title_cn": "内战愈演愈烈，欧盟将制裁苏丹黄金贸易",
    "summary": "The European Union approved new trade prohibitions on Sudan’s gold sector as the country’s civil war enters its fourth year.",
    "link": "https://www.bloomberg.com/news/articles/2026-07-13/eu-to-sanction-sudan-s-gold-trade-as-civil-war-rages",
    "published": "Mon, 13 Jul 2026 08:47:16 GMT",
    "source": "International",
    "fetched_at": "2026-07-13T15:58:39.760712"
  },
  {
    "id": "752366868370",
    "title": "DOJ Is Probing Claims UAW’s President Abused Union Position",
    "title_cn": "司法部正在调查 UAW 主席滥用工会职位的指控",
    "summary": "The US Justice Department launched a grand jury investigation into allegations that the head of the United Auto Workers pressured another high-ranking union official to secure benefits for his fiancée and her sister, according to internal communications within the labor organization.",
    "link": "https://www.bloomberg.com/news/articles/2026-07-12/doj-investigating-allegations-against-uaw-president-shawn-fain",
    "published": "Sun, 12 Jul 2026 19:25:59 GMT",
    "source": "International",
    "fetched_at": "2026-07-13T15:58:39.886051"
  },
  {
    "id": "216c96f10123",
    "title": "How the Sudden Death of Sen. Graham Will Shift the GOP",
    "title_cn": "参议员格雷厄姆的突然去世将如何改变共和党",
    "summary": "Jon Lieber of the Eurasia Group reflects on how the sudden death of Senator Lindsey Graham of South Carolina will impact President Donald Trump and foreign policy in the Republican party. He speaks on \"Bloomberg Surveillance.\" Graham died on Saturday at age 71. (Source: Bloomberg)",
    "link": "https://www.bloomberg.com/news/videos/2026-07-13/how-the-sudden-death-of-sen-graham-will-shift-the-gop-video",
    "published": "Mon, 13 Jul 2026 12:20:02 GMT",
    "source": "International",
    "fetched_at": "2026-07-13T15:58:40.011948"
  },
  {
    "id": "15f9ccbf9d86",
    "title": "California Lawmakers Push Fix for Hollywood Tax Credits",
    "title_cn": "加州立法者推动修复好莱坞税收抵免",
    "summary": "A California business tax credit cap aimed at saving $4 billion threatens to drive away film and television production, according to a letter signed by a bipartisan group of lawmakers who demanded a quick fix to the budget signed by Governor Gavin Newsom.",
    "link": "https://www.bloomberg.com/news/articles/2026-07-13/newsom-budget-kneecapped-hollywood-tax-credit-lawmakers-say",
    "published": "Mon, 13 Jul 2026 02:36:48 GMT",
    "source": "International",
    "fetched_at": "2026-07-13T15:58:40.122758"
  },
  {
    "id": "b9f4a963647e",
    "title": "Hungary Is Poised to Oust President in Rollback of Orban Era",
    "title_cn": "匈牙利准备罢黜总统，重返欧尔班时代",
    "summary": "Hungarian lawmakers are set to oust the Viktor Orban-allied president as Prime Minister Peter Magyar seeks a clean break from his nationalist predecessor.",
    "link": "https://www.bloomberg.com/news/articles/2026-07-13/hungary-is-poised-to-oust-president-in-a-rollback-of-orban-era",
    "published": "Mon, 13 Jul 2026 04:15:00 GMT",
    "source": "International",
    "fetched_at": "2026-07-13T15:58:40.255596"
  },
  {
    "id": "677a7e1eb8d7",
    "title": "Macron Calls on EU to Deliver More Joint Defense Projects",
    "title_cn": "马克龙呼吁欧盟实施更多联合防御项目",
    "summary": "French President Emmanuel Macron urged European Union allies to pursue more joint defense projects as he sought to turn the page on a failed partnership with Germany to build a new fighter jet.",
    "link": "https://www.bloomberg.com/news/articles/2026-07-13/macron-calls-on-eu-allies-to-deliver-more-joint-defense-projects",
    "published": "Mon, 13 Jul 2026 11:10:57 GMT",
    "source": "International",
    "fetched_at": "2026-07-13T15:58:40.393075"
  },
  {
    "id": "d5f4f36e8791",
    "title": "Morgan Stanley’s $2.5 Billion Parking-Meter Sale Roils Chicago Council",
    "title_cn": "摩根士丹利 25 亿美元出售停车计时器引发芝加哥议会骚乱",
    "summary": "For almost two decades, Chicago has been stewing over a $1.15 billion deal to lease 36,000 parking meters to an investor group led by Morgan Stanley. Now, with the meters set to change hands, the city council is seizing on an opening to push back.",
    "link": "https://www.bloomberg.com/news/articles/2026-07-13/morgan-stanley-s-2-5-billion-parking-sale-roils-chicago-council",
    "published": "Mon, 13 Jul 2026 12:00:00 GMT",
    "source": "International",
    "fetched_at": "2026-07-13T15:58:40.527333"
  },
  {
    "id": "ab60a9715251",
    "title": "Graham’s Death Leaves Void for Trump, Global Allies",
    "title_cn": "格雷厄姆的去世给特朗普和全球盟友留下了空白",
    "summary": "On Ukraine, Iran and more, Graham held Trump’s ear like few others.",
    "link": "https://www.bloomberg.com/news/newsletters/2026-07-13/lindsey-graham-s-death-leaves-void-for-trump-global-allies",
    "published": "Mon, 13 Jul 2026 11:37:03 GMT",
    "source": "International",
    "fetched_at": "2026-07-13T15:58:40.633171"
  },
  {
    "id": "2b45878cde16",
    "title": "UK Civil Servant Challenges Firing Over Mandelson Appointment",
    "title_cn": "英国公务员挑战解雇曼德尔森任命",
    "summary": "The former head of the UK Foreign Office, who was fired by Keir Starmer in the row over Peter Mandelson’s links to Jeffrey Epstein, has submitted a legal challenge against the government.",
    "link": "https://www.bloomberg.com/news/articles/2026-07-13/uk-civil-servant-challenges-firing-over-mandelson-appointment",
    "published": "Mon, 13 Jul 2026 11:28:45 GMT",
    "source": "International",
    "fetched_at": "2026-07-13T15:58:40.765577"
  },
  {
    "id": "66c1f65f019f",
    "title": "Uproar Over High Doctors Wages Hits Polish Ruling Party Support",
    "title_cn": "医生高薪引起的轩然大波打击了波兰执政党的支持",
    "summary": "Prime Minister Donald Tusk’s ruling party is losing ground in polls a year before elections, following uproar over how much doctors’ salaries are eating up from the strained healthcare budget.",
    "link": "https://www.bloomberg.com/news/articles/2026-07-13/uproar-over-high-doctors-wages-hits-polish-ruling-party-support",
    "published": "Mon, 13 Jul 2026 11:14:09 GMT",
    "source": "International",
    "fetched_at": "2026-07-13T15:58:41.035052"
  },
  {
    "id": "077d56254b46",
    "title": "Ukraine Says It Hit More Oil and Dry-Cargo Ships in Sea of Azov",
    "title_cn": "乌克兰称在亚速海击中更多油船和干货船",
    "summary": "Ukrainian forces hit seven Russian fuel tankers, five dry-cargo vessels and a batch of other ships in the Sea of Azov as Kyiv expands the scope of its maritime attacks in the area.",
    "link": "https://www.bloomberg.com/news/articles/2026-07-13/ukraine-says-it-hit-more-oil-and-dry-cargo-ships-in-sea-of-azov",
    "published": "Mon, 13 Jul 2026 11:12:08 GMT",
    "source": "International",
    "fetched_at": "2026-07-13T15:58:41.152461"
  },
  {
    "id": "8a0def8bf0f8",
    "title": "Europe Looks for a Musk-Free Path to Space",
    "title_cn": "欧洲寻找一条无麝香的太空之路",
    "summary": "Europe is competing with US, China and Russia to establish a sovereign space industry.",
    "link": "https://www.bloomberg.com/news/newsletters/2026-07-13/as-elsewhere-europe-has-a-long-way-to-travel-to-catch-up-in-the-space-race",
    "published": "Mon, 13 Jul 2026 09:59:03 GMT",
    "source": "International",
    "fetched_at": "2026-07-13T15:58:41.321800"
  },
  {
    "id": "84c75c1ce540",
    "title": "Long Night of Jakarta Raids Found Gold Bars, Wads of Cash",
    "title_cn": "雅加达长夜突袭发现金条和大量现金",
    "summary": "Diners at de’Clan Signature, an eatery in the low-rise South Jakarta neighborhood of Cipete, knew something was up when heavily armed police converged upon the restaurant last Wednesday afternoon.",
    "link": "https://www.bloomberg.com/news/articles/2026-07-13/long-night-of-jakarta-raids-that-found-gold-bars-wads-of-cash",
    "published": "Mon, 13 Jul 2026 04:23:01 GMT",
    "source": "International",
    "fetched_at": "2026-07-13T15:58:41.431769"
  },
  {
    "id": "2ca7a85bde46",
    "title": "As Milei’s Aura Fades, Argentina Starts to Look for a Third Way",
    "title_cn": "米莱光环褪去，阿根廷开始寻找第三条路",
    "summary": "Corruption was once Javier Milei’s strongest card against the Peronist movement that dominated Argentine politics for decades. Now it’s just one of several vulnerabilities that are damaging the libertarian president’s brand and giving wings to the opposition’s comeback plans.",
    "link": "https://www.bloomberg.com/news/articles/2026-07-13/as-milei-s-aura-fades-argentina-starts-to-look-for-a-third-way",
    "published": "Mon, 13 Jul 2026 09:00:00 GMT",
    "source": "International",
    "fetched_at": "2026-07-13T15:58:41.554857"
  }
]